{
  "date": "2020-12-09",
  "placements": [
    {
      "id": 9,
      "merchant_site_hostname": "audible.com",
      "meta_key": null,
      "fi_name": "Default",
      "bank_identification_number": null,
      "cuid": "",
      "par": null,
      "card_customer_key": null,
      "account_customer_key": null,
      "status": "ABANDONED_QUICKSTART",
      "status_message": null,
      "termination_type": "",
      "custom_data": {
        "cardsavr_card_data": {
          "meta_key": "MB9800639"
        }
      },
      "source": null,
      "time_elapsed": 408163,
      "first_6": null,
      "first_7": null,
      "first_8": null,
      "card_type": null,
      "trace": "{\"location\":\"[at /home/vbs/src/main.ts:115:20]\",\"trace\":{\"key\":\"rhc2k0igx0mr0m9sl309\",\"vbs_pid\":\"3EjHCgC7fro\"},\"tenant\":\"advancial-prod\",\"fi\":\"Default\",\"job_id\":9,\"site_hostname\":\"audible.com\",\"user\":\"ma*@gmail.com\"}",
      "place_card_on_single_site_job_id": 9,
      "financial_institution_id": 2,
      "merchant_site_id": 15,
      "agent_session_id": null,
      "bin_id": null,
      "html": null,
      "queue_name": "vbs_queue",
      "job_type": null,
      "recording_path": "https://s3.console.aws.amazon.com/s3/object/swch-768009573690-global-logs/advancial-prod/vbs/VBSRecording/2020-12-09/audible.com/1607502798891.json",
      "terminating_state": "check_for_merchant_account_data",
      "terminating_state_status": "ABANDONED_QUICKSTART",
      "fi_lookup_key": "default",
      "is_expected_failure": false,
      "unrestricted": true,
      "email_sent": false,
      "account_linked_on": null,
      "job_ready_on": null,
      "job_created_on": null,
      "completed_on": "2020-12-09T08:33:20.065Z",
      "created_on": "2020-12-09T08:33:20.210Z",
      "last_updated_on": null,
      "_instance": "advancial-prod"
    },
    {
      "id": 4473,
      "merchant_site_hostname": "amazon.com",
      "meta_key": null,
      "fi_name": "Acme Credit Union",
      "bank_identification_number": null,
      "cuid": "",
      "par": null,
      "card_customer_key": null,
      "account_customer_key": null,
      "status": "ABANDONED_QUICKSTART",
      "status_message": null,
      "termination_type": "",
      "custom_data": {
        "cardsavr_card_data": {
          "meta_key": "JD8950342"
        }
      },
      "source": null,
      "time_elapsed": 375070,
      "first_6": "ea90622fa6e23cf933bfdf5db28473fb",
      "first_7": "deb1f3677d0bd935f5e0c735eb62ae37",
      "first_8": "59297c3fb1a4580b23ce6c1b5d667d67",
      "card_type": null,
      "trace": "{\"location\":\"[at /home/vbs/src/main.ts:115:20]\",\"trace\":{\"key\":\"es60eesmwugfztbyi61s\",\"vbs_pid\":\"H5NeKj1h6RU\"},\"tenant\":\"ss01\",\"fi\":\"Acme Credit Union\",\"job_id\":4432,\"site_hostname\":\"amazon.com\",\"user\":\"di*@gmail.com\"}",
      "place_card_on_single_site_job_id": 4432,
      "financial_institution_id": 26,
      "merchant_site_id": 12,
      "agent_session_id": null,
      "bin_id": null,
      "html": null,
      "queue_name": "vbs_queue",
      "job_type": null,
      "recording_path": "https://s3.console.aws.amazon.com/s3/object/swch-768009573690-global-logs/ss01/vbs/VBSRecording/2020-12-09/amazon.com/1607537713594.json",
      "terminating_state": "check_for_merchant_account_data",
      "terminating_state_status": "ABANDONED_QUICKSTART",
      "fi_lookup_key": "acmecu",
      "is_expected_failure": false,
      "unrestricted": true,
      "email_sent": false,
      "account_linked_on": null,
      "job_ready_on": null,
      "job_created_on": null,
      "completed_on": "2020-12-09T18:15:14.034Z",
      "created_on": "2020-12-09T18:15:14.172Z",
      "last_updated_on": null,
      "_instance": "ss01"
    },
    {
      "id": 4474,
      "merchant_site_hostname": "spotify.com",
      "meta_key": null,
      "fi_name": "Acme Credit Union",
      "bank_identification_number": null,
      "cuid": "",
      "par": null,
      "card_customer_key": null,
      "account_customer_key": null,
      "status": "ABANDONED_QUICKSTART",
      "status_message": null,
      "termination_type": "",
      "custom_data": {
        "cardsavr_card_data": {
          "meta_key": "JD8950342"
        }
      },
      "source": null,
      "time_elapsed": 394188,
      "first_6": "ea90622fa6e23cf933bfdf5db28473fb",
      "first_7": "deb1f3677d0bd935f5e0c735eb62ae37",
      "first_8": "59297c3fb1a4580b23ce6c1b5d667d67",
      "card_type": null,
      "trace": "{\"location\":\"[at /home/vbs/src/main.ts:115:20]\",\"trace\":{\"key\":\"es60eesmwugfztbyi61s\",\"vbs_pid\":\"JKMMqpmVoMA\"},\"tenant\":\"ss01\",\"fi\":\"Acme Credit Union\",\"job_id\":4430,\"site_hostname\":\"spotify.com\",\"user\":\"di*@gmail.com\"}",
      "place_card_on_single_site_job_id": 4430,
      "financial_institution_id": 26,
      "merchant_site_id": 19,
      "agent_session_id": null,
      "bin_id": null,
      "html": null,
      "queue_name": "vbs_queue",
      "job_type": null,
      "recording_path": "https://s3.console.aws.amazon.com/s3/object/swch-768009573690-global-logs/ss01/vbs/VBSRecording/2020-12-09/spotify.com/1607537732734.json",
      "terminating_state": "check_for_merchant_account_data",
      "terminating_state_status": "ABANDONED_QUICKSTART",
      "fi_lookup_key": "acmecu",
      "is_expected_failure": false,
      "unrestricted": true,
      "email_sent": false,
      "account_linked_on": null,
      "job_ready_on": null,
      "job_created_on": null,
      "completed_on": "2020-12-09T18:15:33.464Z",
      "created_on": "2020-12-09T18:15:33.608Z",
      "last_updated_on": null,
      "_instance": "ss01"
    },
    {
      "id": 4475,
      "merchant_site_hostname": "hulu.com",
      "meta_key": null,
      "fi_name": "Acme Credit Union",
      "bank_identification_number": null,
      "cuid": "",
      "par": null,
      "card_customer_key": null,
      "account_customer_key": null,
      "status": "ABANDONED_QUICKSTART",
      "status_message": null,
      "termination_type": "",
      "custom_data": {
        "cardsavr_card_data": {
          "meta_key": "JD8950342"
        }
      },
      "source": null,
      "time_elapsed": 418136,
      "first_6": "ea90622fa6e23cf933bfdf5db28473fb",
      "first_7": "deb1f3677d0bd935f5e0c735eb62ae37",
      "first_8": "59297c3fb1a4580b23ce6c1b5d667d67",
      "card_type": null,
      "trace": "{\"location\":\"[at /home/vbs/src/main.ts:119:20]\",\"trace\":{\"key\":\"es60eesmwugfztbyi61s\",\"vbs_pid\":\"qGRGSO3m_Ek\"},\"tenant\":\"ss01\",\"fi\":\"Acme Credit Union\",\"job_id\":4431,\"site_hostname\":\"hulu.com\",\"user\":\"di*@gmail.com\"}",
      "place_card_on_single_site_job_id": 4431,
      "financial_institution_id": 26,
      "merchant_site_id": 52,
      "agent_session_id": null,
      "bin_id": null,
      "html": null,
      "queue_name": "vbs_queue",
      "job_type": null,
      "recording_path": "https://s3.console.aws.amazon.com/s3/object/swch-768009573690-global-logs/ss01/vbs/VBSRecording/2020-12-09/hulu.com/1607537790294.json",
      "terminating_state": "check_for_merchant_account_data",
      "terminating_state_status": "ABANDONED_QUICKSTART",
      "fi_lookup_key": "acmecu",
      "is_expected_failure": false,
      "unrestricted": true,
      "email_sent": false,
      "account_linked_on": null,
      "job_ready_on": null,
      "job_created_on": null,
      "completed_on": "2020-12-09T18:16:31.603Z",
      "created_on": "2020-12-09T18:16:31.732Z",
      "last_updated_on": null,
      "_instance": "ss01"
    },
    {
      "id": 4476,
      "merchant_site_hostname": "amazon.com",
      "meta_key": null,
      "fi_name": "Default",
      "bank_identification_number": null,
      "cuid": "",
      "par": null,
      "card_customer_key": null,
      "account_customer_key": null,
      "status": "ABANDONED_QUICKSTART",
      "status_message": null,
      "termination_type": "",
      "custom_data": {
        "cardsavr_card_data": {
          "meta_key": "PH0793311"
        }
      },
      "source": null,
      "time_elapsed": 373604,
      "first_6": "248a90ab746c05937cd0f8aaecbe7d64",
      "first_7": "87e3647a0d73221cc06836411d6753c7",
      "first_8": "61218b9de78ea7d595a87aa2c8c5e113",
      "card_type": null,
      "trace": "{\"location\":\"[at /home/vbs/src/main.ts:119:20]\",\"trace\":{\"key\":\"15box1p0fjv2f7u7ydt3\",\"vbs_pid\":\"NuLGmPl7SBk\"},\"tenant\":\"ss01\",\"fi\":\"Default\",\"job_id\":4435,\"site_hostname\":\"amazon.com\",\"user\":\"tr*@gmail.com\"}",
      "place_card_on_single_site_job_id": 4435,
      "financial_institution_id": 25,
      "merchant_site_id": 12,
      "agent_session_id": null,
      "bin_id": null,
      "html": null,
      "queue_name": "vbs_queue",
      "job_type": null,
      "recording_path": "https://s3.console.aws.amazon.com/s3/object/swch-768009573690-global-logs/ss01/vbs/VBSRecording/2020-12-09/amazon.com/1607538689236.json",
      "terminating_state": "check_for_merchant_account_data",
      "terminating_state_status": "ABANDONED_QUICKSTART",
      "fi_lookup_key": "default",
      "is_expected_failure": false,
      "unrestricted": true,
      "email_sent": false,
      "account_linked_on": null,
      "job_ready_on": null,
      "job_created_on": null,
      "completed_on": "2020-12-09T18:31:29.828Z",
      "created_on": "2020-12-09T18:31:29.979Z",
      "last_updated_on": null,
      "_instance": "ss01"
    },
    {
      "id": 4477,
      "merchant_site_hostname": "uber.com",
      "meta_key": null,
      "fi_name": "Default",
      "bank_identification_number": null,
      "cuid": "",
      "par": null,
      "card_customer_key": null,
      "account_customer_key": null,
      "status": "ABANDONED_QUICKSTART",
      "status_message": null,
      "termination_type": "",
      "custom_data": {
        "cardsavr_card_data": {
          "meta_key": "PH0793311"
        }
      },
      "source": null,
      "time_elapsed": 393516,
      "first_6": "248a90ab746c05937cd0f8aaecbe7d64",
      "first_7": "87e3647a0d73221cc06836411d6753c7",
      "first_8": "61218b9de78ea7d595a87aa2c8c5e113",
      "card_type": null,
      "trace": "{\"location\":\"[at /home/vbs/src/main.ts:119:20]\",\"trace\":{\"key\":\"15box1p0fjv2f7u7ydt3\",\"vbs_pid\":\"-8zoUwcibRM\"},\"tenant\":\"ss01\",\"fi\":\"Default\",\"job_id\":4433,\"site_hostname\":\"uber.com\",\"user\":\"tr*@gmail.com\"}",
      "place_card_on_single_site_job_id": 4433,
      "financial_institution_id": 25,
      "merchant_site_id": 109,
      "agent_session_id": null,
      "bin_id": null,
      "html": null,
      "queue_name": "vbs_queue",
      "job_type": null,
      "recording_path": "https://s3.console.aws.amazon.com/s3/object/swch-768009573690-global-logs/ss01/vbs/VBSRecording/2020-12-09/uber.com/1607538701576.json",
      "terminating_state": "check_for_merchant_account_data",
      "terminating_state_status": "ABANDONED_QUICKSTART",
      "fi_lookup_key": "default",
      "is_expected_failure": false,
      "unrestricted": true,
      "email_sent": false,
      "account_linked_on": null,
      "job_ready_on": null,
      "job_created_on": null,
      "completed_on": "2020-12-09T18:31:42.017Z",
      "created_on": "2020-12-09T18:31:42.170Z",
      "last_updated_on": null,
      "_instance": "ss01"
    },
    {
      "id": 4478,
      "merchant_site_hostname": "netflix.com",
      "meta_key": null,
      "fi_name": "Default",
      "bank_identification_number": null,
      "cuid": "",
      "par": null,
      "card_customer_key": null,
      "account_customer_key": null,
      "status": "ABANDONED_QUICKSTART",
      "status_message": null,
      "termination_type": "",
      "custom_data": {
        "cardsavr_card_data": {
          "meta_key": "PH0793311"
        }
      },
      "source": null,
      "time_elapsed": 378920,
      "first_6": "248a90ab746c05937cd0f8aaecbe7d64",
      "first_7": "87e3647a0d73221cc06836411d6753c7",
      "first_8": "61218b9de78ea7d595a87aa2c8c5e113",
      "card_type": null,
      "trace": "{\"location\":\"[at /home/vbs/src/main.ts:119:20]\",\"trace\":{\"key\":\"15box1p0fjv2f7u7ydt3\",\"vbs_pid\":\"Uv2YF7YJ3zg\"},\"tenant\":\"ss01\",\"fi\":\"Default\",\"job_id\":4434,\"site_hostname\":\"netflix.com\",\"user\":\"tr*@gmail.com\"}",
      "place_card_on_single_site_job_id": 4434,
      "financial_institution_id": 25,
      "merchant_site_id": 40,
      "agent_session_id": null,
      "bin_id": null,
      "html": null,
      "queue_name": "vbs_queue",
      "job_type": null,
      "recording_path": "https://s3.console.aws.amazon.com/s3/object/swch-768009573690-global-logs/ss01/vbs/VBSRecording/2020-12-09/netflix.com/1607538729923.json",
      "terminating_state": "check_for_merchant_account_data",
      "terminating_state_status": "ABANDONED_QUICKSTART",
      "fi_lookup_key": "default",
      "is_expected_failure": false,
      "unrestricted": true,
      "email_sent": false,
      "account_linked_on": null,
      "job_ready_on": null,
      "job_created_on": null,
      "completed_on": "2020-12-09T18:32:10.469Z",
      "created_on": "2020-12-09T18:32:10.584Z",
      "last_updated_on": null,
      "_instance": "ss01"
    },
    {
      "id": 4479,
      "merchant_site_hostname": "amazon.com",
      "meta_key": null,
      "fi_name": "Acme Credit Union",
      "bank_identification_number": null,
      "cuid": "",
      "par": null,
      "card_customer_key": null,
      "account_customer_key": null,
      "status": "ABANDONED_QUICKSTART",
      "status_message": null,
      "termination_type": "",
      "custom_data": {
        "cardsavr_card_data": {
          "meta_key": "JW1568781"
        }
      },
      "source": null,
      "time_elapsed": 376287,
      "first_6": "4986da0bb3b895d590f032133f2f6aaf",
      "first_7": "c1d3ce5a9f895477170184885e2b0667",
      "first_8": "c7e254eaa49441d878eda404dbb3f2c1",
      "card_type": null,
      "trace": "{\"location\":\"[at /home/vbs/src/main.ts:119:20]\",\"trace\":{\"key\":\"8e21mx24ryd0txlt8xc7\",\"vbs_pid\":\"EeO8Us5jcsU\"},\"tenant\":\"ss01\",\"fi\":\"Acme Credit Union\",\"job_id\":4438,\"site_hostname\":\"amazon.com\",\"user\":\"jo*@digitalonboarding.co\"}",
      "place_card_on_single_site_job_id": 4438,
      "financial_institution_id": 26,
      "merchant_site_id": 12,
      "agent_session_id": null,
      "bin_id": null,
      "html": null,
      "queue_name": "vbs_queue",
      "job_type": null,
      "recording_path": "https://s3.console.aws.amazon.com/s3/object/swch-768009573690-global-logs/ss01/vbs/VBSRecording/2020-12-09/amazon.com/1607546237633.json",
      "terminating_state": "check_for_merchant_account_data",
      "terminating_state_status": "ABANDONED_QUICKSTART",
      "fi_lookup_key": "acmecu",
      "is_expected_failure": false,
      "unrestricted": true,
      "email_sent": false,
      "account_linked_on": null,
      "job_ready_on": null,
      "job_created_on": null,
      "completed_on": "2020-12-09T20:37:18.118Z",
      "created_on": "2020-12-09T20:37:18.249Z",
      "last_updated_on": null,
      "_instance": "ss01"
    },
    {
      "id": 4480,
      "merchant_site_hostname": "apple.com",
      "meta_key": null,
      "fi_name": "Acme Credit Union",
      "bank_identification_number": null,
      "cuid": "",
      "par": null,
      "card_customer_key": null,
      "account_customer_key": null,
      "status": "ABANDONED_QUICKSTART",
      "status_message": null,
      "termination_type": "",
      "custom_data": {
        "cardsavr_card_data": {
          "meta_key": "JW1568781"
        }
      },
      "source": null,
      "time_elapsed": 403733,
      "first_6": "4986da0bb3b895d590f032133f2f6aaf",
      "first_7": "c1d3ce5a9f895477170184885e2b0667",
      "first_8": "c7e254eaa49441d878eda404dbb3f2c1",
      "card_type": null,
      "trace": "{\"location\":\"[at /home/vbs/src/main.ts:119:20]\",\"trace\":{\"key\":\"8e21mx24ryd0txlt8xc7\",\"vbs_pid\":\"WbRNweOPCpI\"},\"tenant\":\"ss01\",\"fi\":\"Acme Credit Union\",\"job_id\":4437,\"site_hostname\":\"apple.com\",\"user\":\"jo*@digitalonboarding.co\"}",
      "place_card_on_single_site_job_id": 4437,
      "financial_institution_id": 26,
      "merchant_site_id": 14,
      "agent_session_id": null,
      "bin_id": null,
      "html": null,
      "queue_name": "vbs_queue",
      "job_type": null,
      "recording_path": "https://s3.console.aws.amazon.com/s3/object/swch-768009573690-global-logs/ss01/vbs/VBSRecording/2020-12-09/apple.com/1607546265061.json",
      "terminating_state": "check_for_merchant_account_data",
      "terminating_state_status": "ABANDONED_QUICKSTART",
      "fi_lookup_key": "acmecu",
      "is_expected_failure": false,
      "unrestricted": true,
      "email_sent": false,
      "account_linked_on": null,
      "job_ready_on": null,
      "job_created_on": null,
      "completed_on": "2020-12-09T20:37:45.919Z",
      "created_on": "2020-12-09T20:37:46.043Z",
      "last_updated_on": null,
      "_instance": "ss01"
    },
    {
      "id": 4481,
      "merchant_site_hostname": "hulu.com",
      "meta_key": null,
      "fi_name": "Acme Credit Union",
      "bank_identification_number": null,
      "cuid": "",
      "par": null,
      "card_customer_key": null,
      "account_customer_key": null,
      "status": "ABANDONED_QUICKSTART",
      "status_message": null,
      "termination_type": "",
      "custom_data": {
        "cardsavr_card_data": {
          "meta_key": "JW1568781"
        }
      },
      "source": null,
      "time_elapsed": 422293,
      "first_6": "4986da0bb3b895d590f032133f2f6aaf",
      "first_7": "c1d3ce5a9f895477170184885e2b0667",
      "first_8": "c7e254eaa49441d878eda404dbb3f2c1",
      "card_type": null,
      "trace": "{\"location\":\"[at /home/vbs/src/main.ts:119:20]\",\"trace\":{\"key\":\"8e21mx24ryd0txlt8xc7\",\"vbs_pid\":\"4smxLZlPEAc\"},\"tenant\":\"ss01\",\"fi\":\"Acme Credit Union\",\"job_id\":4436,\"site_hostname\":\"hulu.com\",\"user\":\"jo*@digitalonboarding.co\"}",
      "place_card_on_single_site_job_id": 4436,
      "financial_institution_id": 26,
      "merchant_site_id": 52,
      "agent_session_id": null,
      "bin_id": null,
      "html": null,
      "queue_name": "vbs_queue",
      "job_type": null,
      "recording_path": "https://s3.console.aws.amazon.com/s3/object/swch-768009573690-global-logs/ss01/vbs/VBSRecording/2020-12-09/hulu.com/1607546322718.json",
      "terminating_state": "check_for_merchant_account_data",
      "terminating_state_status": "ABANDONED_QUICKSTART",
      "fi_lookup_key": "acmecu",
      "is_expected_failure": false,
      "unrestricted": true,
      "email_sent": false,
      "account_linked_on": null,
      "job_ready_on": null,
      "job_created_on": null,
      "completed_on": "2020-12-09T20:38:44.086Z",
      "created_on": "2020-12-09T20:38:44.220Z",
      "last_updated_on": null,
      "_instance": "ss01"
    }
  ]
}