{
  "date": "2022-06-26",
  "placements": [
    {
      "id": 1220,
      "merchant_site_hostname": "uber.com",
      "meta_key": null,
      "fi_name": "Default",
      "bank_identification_number": null,
      "cuid": "8lqmpj4po7955mi1643c",
      "par": null,
      "card_customer_key": null,
      "account_customer_key": "109$8lqmpj4po7955mi1643c",
      "status": "ABANDONED_QUICKSTART",
      "status_message": null,
      "termination_type": "NEVER_STARTED",
      "custom_data": null,
      "source": null,
      "time_elapsed": 553433,
      "first_6": null,
      "first_7": null,
      "first_8": null,
      "card_type": null,
      "trace": "{\"key\":\"8lqmpj4po7955mi1643c\"}",
      "place_card_on_single_site_job_id": 1220,
      "financial_institution_id": 2,
      "merchant_site_id": 109,
      "agent_session_id": null,
      "bin_id": null,
      "html": null,
      "queue_name": "vbs_lambda_queue",
      "job_type": "rpa:rpa",
      "recording_path": null,
      "terminating_state": "wait_for_quick_start_credentials",
      "terminating_state_status": "abandoned_quickstart",
      "fi_lookup_key": "default",
      "is_expected_failure": false,
      "unrestricted": true,
      "email_sent": false,
      "account_linked_on": null,
      "job_ready_on": null,
      "job_created_on": null,
      "completed_on": "2022-06-26T16:48:06.654Z",
      "created_on": "2022-06-26T16:48:06.756Z",
      "last_updated_on": null,
      "_instance": "advancial-prod"
    },
    {
      "id": 13301,
      "merchant_site_hostname": "lyft.com",
      "meta_key": "TM3791844",
      "fi_name": "ORNL Federal Credit Union",
      "bank_identification_number": "443238",
      "cuid": "iw3khmhzcg507hb9aoks",
      "par": "C7GhmVuvOhMtV6MVNTPAWVrFuY5M=",
      "card_customer_key": "C7GhmVuvOhMtV6MVNTPAWVrFuY5M=",
      "account_customer_key": "149$iw3khmhzcg507hb9aoks",
      "status": "TIMEOUT_TFA",
      "status_message": "Unable to automatically update your card due to invalid or missing two-factor authentication.",
      "termination_type": "USER_DATA_FAILURE",
      "custom_data": null,
      "source": null,
      "time_elapsed": null,
      "first_6": "5c1e554271a9ec407e38785f9567ef55",
      "first_7": "dd56968ae138ab97f648da8ef7e212ed",
      "first_8": "2973459509b210dd7188967853b25b39",
      "card_type": null,
      "trace": null,
      "place_card_on_single_site_job_id": 13142,
      "financial_institution_id": 134,
      "merchant_site_id": 149,
      "agent_session_id": null,
      "bin_id": 57662,
      "html": null,
      "queue_name": "vbs_lambda_queue",
      "job_type": "rpa:rpa",
      "recording_path": null,
      "terminating_state": null,
      "terminating_state_status": null,
      "fi_lookup_key": "ornlfcu",
      "is_expected_failure": false,
      "unrestricted": true,
      "email_sent": false,
      "account_linked_on": null,
      "job_ready_on": null,
      "job_created_on": null,
      "completed_on": "2022-06-26T20:48:00.474Z",
      "created_on": "2022-06-26T20:48:00.474Z",
      "last_updated_on": null,
      "_instance": "ss01"
    },
    {
      "id": 13302,
      "merchant_site_hostname": "kroger.com",
      "meta_key": "TM3791844",
      "fi_name": "ORNL Federal Credit Union",
      "bank_identification_number": "443238",
      "cuid": "iw3khmhzcg507hb9aoks",
      "par": "C7GhmVuvOhMtV6MVNTPAWVrFuY5M=",
      "card_customer_key": "C7GhmVuvOhMtV6MVNTPAWVrFuY5M=",
      "account_customer_key": "6$iw3khmhzcg507hb9aoks",
      "status": "TOO_MANY_LOGIN_FAILURES",
      "status_message": "Unable to automatically update your card due to invalid username/password.",
      "termination_type": "USER_DATA_FAILURE",
      "custom_data": null,
      "source": null,
      "time_elapsed": 412727,
      "first_6": "5c1e554271a9ec407e38785f9567ef55",
      "first_7": "dd56968ae138ab97f648da8ef7e212ed",
      "first_8": "2973459509b210dd7188967853b25b39",
      "card_type": null,
      "trace": "{\"key\":\"iw3khmhzcg507hb9aoks\"}",
      "place_card_on_single_site_job_id": 13143,
      "financial_institution_id": 134,
      "merchant_site_id": 6,
      "agent_session_id": null,
      "bin_id": 57662,
      "html": null,
      "queue_name": "vbs_lambda_queue",
      "job_type": "rpa:rpa",
      "recording_path": null,
      "terminating_state": "login_username",
      "terminating_state_status": "too_many_login_failures",
      "fi_lookup_key": "ornlfcu",
      "is_expected_failure": false,
      "unrestricted": true,
      "email_sent": false,
      "account_linked_on": null,
      "job_ready_on": null,
      "job_created_on": null,
      "completed_on": "2022-06-26T20:48:11.599Z",
      "created_on": "2022-06-26T20:48:11.673Z",
      "last_updated_on": null,
      "_instance": "ss01"
    },
    {
      "id": 13303,
      "merchant_site_hostname": "expedia.com",
      "meta_key": "TM3791844",
      "fi_name": "ORNL Federal Credit Union",
      "bank_identification_number": "443238",
      "cuid": "iw3khmhzcg507hb9aoks",
      "par": "C7GhmVuvOhMtV6MVNTPAWVrFuY5M=",
      "card_customer_key": "C7GhmVuvOhMtV6MVNTPAWVrFuY5M=",
      "account_customer_key": "8$iw3khmhzcg507hb9aoks",
      "status": "ABANDONED_QUICKSTART",
      "status_message": null,
      "termination_type": "NEVER_STARTED",
      "custom_data": null,
      "source": null,
      "time_elapsed": 552795,
      "first_6": "5c1e554271a9ec407e38785f9567ef55",
      "first_7": "dd56968ae138ab97f648da8ef7e212ed",
      "first_8": "2973459509b210dd7188967853b25b39",
      "card_type": null,
      "trace": "{\"key\":\"iw3khmhzcg507hb9aoks\"}",
      "place_card_on_single_site_job_id": 13144,
      "financial_institution_id": 134,
      "merchant_site_id": 8,
      "agent_session_id": null,
      "bin_id": 57662,
      "html": null,
      "queue_name": "vbs_lambda_queue",
      "job_type": "rpa:rpa",
      "recording_path": null,
      "terminating_state": "wait_for_quick_start_credentials",
      "terminating_state_status": "abandoned_quickstart",
      "fi_lookup_key": "ornlfcu",
      "is_expected_failure": false,
      "unrestricted": true,
      "email_sent": false,
      "account_linked_on": null,
      "job_ready_on": null,
      "job_created_on": null,
      "completed_on": "2022-06-26T20:50:07.592Z",
      "created_on": "2022-06-26T20:50:07.734Z",
      "last_updated_on": null,
      "_instance": "ss01"
    },
    {
      "id": 13304,
      "merchant_site_hostname": "airbnb.com",
      "meta_key": "TM3791844",
      "fi_name": "ORNL Federal Credit Union",
      "bank_identification_number": "443238",
      "cuid": "iw3khmhzcg507hb9aoks",
      "par": "C7GhmVuvOhMtV6MVNTPAWVrFuY5M=",
      "card_customer_key": "C7GhmVuvOhMtV6MVNTPAWVrFuY5M=",
      "account_customer_key": "88$iw3khmhzcg507hb9aoks",
      "status": "ABANDONED_QUICKSTART",
      "status_message": null,
      "termination_type": "NEVER_STARTED",
      "custom_data": null,
      "source": null,
      "time_elapsed": 588021,
      "first_6": "5c1e554271a9ec407e38785f9567ef55",
      "first_7": "dd56968ae138ab97f648da8ef7e212ed",
      "first_8": "2973459509b210dd7188967853b25b39",
      "card_type": null,
      "trace": "{\"key\":\"iw3khmhzcg507hb9aoks\"}",
      "place_card_on_single_site_job_id": 13145,
      "financial_institution_id": 134,
      "merchant_site_id": 88,
      "agent_session_id": null,
      "bin_id": 57662,
      "html": null,
      "queue_name": "vbs_lambda_queue",
      "job_type": "rpa:rpa",
      "recording_path": null,
      "terminating_state": "wait_for_quick_start_credentials",
      "terminating_state_status": "abandoned_quickstart",
      "fi_lookup_key": "ornlfcu",
      "is_expected_failure": false,
      "unrestricted": true,
      "email_sent": false,
      "account_linked_on": null,
      "job_ready_on": null,
      "job_created_on": null,
      "completed_on": "2022-06-26T20:50:50.992Z",
      "created_on": "2022-06-26T20:50:51.106Z",
      "last_updated_on": null,
      "_instance": "ss01"
    },
    {
      "id": 13305,
      "merchant_site_hostname": "amazon.com",
      "meta_key": null,
      "fi_name": "Lookout Credit Union",
      "bank_identification_number": null,
      "cuid": "9z3847zfvreou48rjw3n",
      "par": null,
      "card_customer_key": null,
      "account_customer_key": "12$9z3847zfvreou48rjw3n",
      "status": "ABANDONED_QUICKSTART",
      "status_message": null,
      "termination_type": "NEVER_STARTED",
      "custom_data": null,
      "source": null,
      "time_elapsed": 553768,
      "first_6": null,
      "first_7": null,
      "first_8": null,
      "card_type": null,
      "trace": "{\"key\":\"9z3847zfvreou48rjw3n\"}",
      "place_card_on_single_site_job_id": 13147,
      "financial_institution_id": 14,
      "merchant_site_id": 12,
      "agent_session_id": null,
      "bin_id": null,
      "html": null,
      "queue_name": "vbs_lambda_queue",
      "job_type": "rpa:rpa",
      "recording_path": null,
      "terminating_state": "wait_for_quick_start_credentials",
      "terminating_state_status": "abandoned_quickstart",
      "fi_lookup_key": "lookoutcu",
      "is_expected_failure": false,
      "unrestricted": true,
      "email_sent": false,
      "account_linked_on": null,
      "job_ready_on": null,
      "job_created_on": null,
      "completed_on": "2022-06-26T23:12:50.193Z",
      "created_on": "2022-06-26T23:12:50.272Z",
      "last_updated_on": null,
      "_instance": "ss01"
    },
    {
      "id": 13306,
      "merchant_site_hostname": "dominos.com",
      "meta_key": null,
      "fi_name": "Lookout Credit Union",
      "bank_identification_number": null,
      "cuid": "9z3847zfvreou48rjw3n",
      "par": null,
      "card_customer_key": null,
      "account_customer_key": "156$9z3847zfvreou48rjw3n",
      "status": "ABANDONED_QUICKSTART",
      "status_message": null,
      "termination_type": "NEVER_STARTED",
      "custom_data": null,
      "source": null,
      "time_elapsed": 552509,
      "first_6": null,
      "first_7": null,
      "first_8": null,
      "card_type": null,
      "trace": "{\"key\":\"9z3847zfvreou48rjw3n\"}",
      "place_card_on_single_site_job_id": 13146,
      "financial_institution_id": 14,
      "merchant_site_id": 156,
      "agent_session_id": null,
      "bin_id": null,
      "html": null,
      "queue_name": "vbs_lambda_queue",
      "job_type": "rpa:rpa",
      "recording_path": null,
      "terminating_state": "wait_for_quick_start_credentials",
      "terminating_state_status": "abandoned_quickstart",
      "fi_lookup_key": "lookoutcu",
      "is_expected_failure": false,
      "unrestricted": true,
      "email_sent": false,
      "account_linked_on": null,
      "job_ready_on": null,
      "job_created_on": null,
      "completed_on": "2022-06-26T23:12:56.815Z",
      "created_on": "2022-06-26T23:12:56.894Z",
      "last_updated_on": null,
      "_instance": "ss01"
    },
    {
      "id": 13307,
      "merchant_site_hostname": "venmo.com",
      "meta_key": null,
      "fi_name": "Lookout Credit Union",
      "bank_identification_number": null,
      "cuid": "9z3847zfvreou48rjw3n",
      "par": null,
      "card_customer_key": null,
      "account_customer_key": "112$9z3847zfvreou48rjw3n",
      "status": "ABANDONED_QUICKSTART",
      "status_message": null,
      "termination_type": "NEVER_STARTED",
      "custom_data": null,
      "source": null,
      "time_elapsed": 570685,
      "first_6": null,
      "first_7": null,
      "first_8": null,
      "card_type": null,
      "trace": "{\"key\":\"9z3847zfvreou48rjw3n\"}",
      "place_card_on_single_site_job_id": 13149,
      "financial_institution_id": 14,
      "merchant_site_id": 112,
      "agent_session_id": null,
      "bin_id": null,
      "html": null,
      "queue_name": "vbs_lambda_queue",
      "job_type": "rpa:rpa",
      "recording_path": null,
      "terminating_state": "wait_for_quick_start_credentials",
      "terminating_state_status": "abandoned_quickstart",
      "fi_lookup_key": "lookoutcu",
      "is_expected_failure": false,
      "unrestricted": true,
      "email_sent": false,
      "account_linked_on": null,
      "job_ready_on": null,
      "job_created_on": null,
      "completed_on": "2022-06-26T23:13:22.828Z",
      "created_on": "2022-06-26T23:13:22.913Z",
      "last_updated_on": null,
      "_instance": "ss01"
    },
    {
      "id": 13308,
      "merchant_site_hostname": "walgreens.com",
      "meta_key": null,
      "fi_name": "Lookout Credit Union",
      "bank_identification_number": null,
      "cuid": "9z3847zfvreou48rjw3n",
      "par": null,
      "card_customer_key": null,
      "account_customer_key": "24$9z3847zfvreou48rjw3n",
      "status": "ABANDONED_QUICKSTART",
      "status_message": null,
      "termination_type": "NEVER_STARTED",
      "custom_data": null,
      "source": null,
      "time_elapsed": 688724,
      "first_6": null,
      "first_7": null,
      "first_8": null,
      "card_type": null,
      "trace": "{\"key\":\"9z3847zfvreou48rjw3n\"}",
      "place_card_on_single_site_job_id": 13148,
      "financial_institution_id": 14,
      "merchant_site_id": 24,
      "agent_session_id": null,
      "bin_id": null,
      "html": null,
      "queue_name": "vbs_lambda_queue",
      "job_type": "rpa:rpa",
      "recording_path": null,
      "terminating_state": "wait_for_quick_start_credentials",
      "terminating_state_status": "abandoned_quickstart",
      "fi_lookup_key": "lookoutcu",
      "is_expected_failure": false,
      "unrestricted": true,
      "email_sent": false,
      "account_linked_on": null,
      "job_ready_on": null,
      "job_created_on": null,
      "completed_on": "2022-06-26T23:15:28.988Z",
      "created_on": "2022-06-26T23:15:29.094Z",
      "last_updated_on": null,
      "_instance": "ss01"
    },
    {
      "id": 7208,
      "merchant_site_hostname": "travelocity.com",
      "meta_key": null,
      "fi_name": "Gather FCU",
      "bank_identification_number": null,
      "cuid": "exrf1xtzvzwmp9sr0e4b",
      "par": null,
      "card_customer_key": null,
      "account_customer_key": "87$exrf1xtzvzwmp9sr0e4b",
      "status": "ABANDONED_QUICKSTART",
      "status_message": null,
      "termination_type": "NEVER_STARTED",
      "custom_data": {
        "digital_onboarding": {
          "team_id": "17d82a56-a10d-4101-99ae-3920f3f7bd0b",
          "contact_id": "69bbfbc2-ff0a-4d3f-92cf-aeccdae4c3f1",
          "page_id": "91fa6159-a868-4e08-8fdc-13184ed8ca27",
          "journey_id": "09527c57-aad6-4948-af2c-5fe61d3e9a2f",
          "slug": "ryzMvbdcd"
        }
      },
      "source": null,
      "time_elapsed": 553323,
      "first_6": null,
      "first_7": null,
      "first_8": null,
      "card_type": null,
      "trace": "{\"key\":\"exrf1xtzvzwmp9sr0e4b\"}",
      "place_card_on_single_site_job_id": 7076,
      "financial_institution_id": 35,
      "merchant_site_id": 87,
      "agent_session_id": null,
      "bin_id": null,
      "html": null,
      "queue_name": "vbs_lambda_queue",
      "job_type": "rpa:rpa",
      "recording_path": null,
      "terminating_state": "ABANDONED_QUICKSTART",
      "terminating_state_status": "ABANDONED_QUICKSTART",
      "fi_lookup_key": "gatherfcu",
      "is_expected_failure": false,
      "unrestricted": true,
      "email_sent": false,
      "account_linked_on": null,
      "job_ready_on": null,
      "job_created_on": null,
      "completed_on": "2022-06-26T04:02:57.912Z",
      "created_on": "2022-06-26T04:02:58.022Z",
      "last_updated_on": null,
      "_instance": "digital-onboarding"
    },
    {
      "id": 7209,
      "merchant_site_hostname": "venmo.com",
      "meta_key": "DA9864073",
      "fi_name": "Columbia CU",
      "bank_identification_number": "423731",
      "cuid": "rfc14pxz7yfozcg662sn",
      "par": "C+tfQfNlx+cl7XKI+3sS6HUyXB/E=",
      "card_customer_key": "C+tfQfNlx+cl7XKI+3sS6HUyXB/E=",
      "account_customer_key": "112$rfc14pxz7yfozcg662sn",
      "status": "SUCCESSFUL",
      "status_message": "Successful",
      "termination_type": "BILLABLE",
      "custom_data": {
        "digital_onboarding": {
          "team_id": "8bd92469-066d-4205-94ba-25eba06dd0e6",
          "contact_id": "40b77253-1952-48c2-939a-633ec576837c",
          "page_id": "2c625c7d-c60d-49e6-8e87-c5ab6cec4292",
          "journey_id": "c3020138-ea7e-456c-9a75-a4ff3782d586",
          "slug": "B1N_sbVKu"
        }
      },
      "source": null,
      "time_elapsed": 243033,
      "first_6": "2a8ac767a3bd78f938bb1571b34b08b7",
      "first_7": "63ebed2dab21e168a6a716dc8f4c3e1f",
      "first_8": "d93b8f11e4fa4a5fc0793b6c6e7f1cef",
      "card_type": null,
      "trace": "{\"key\":\"rfc14pxz7yfozcg662sn\"}",
      "place_card_on_single_site_job_id": 7077,
      "financial_institution_id": 57,
      "merchant_site_id": 112,
      "agent_session_id": null,
      "bin_id": 138,
      "html": null,
      "queue_name": "vbs_lambda_queue",
      "job_type": "rpa:rpa",
      "recording_path": null,
      "terminating_state": "check_if_card_form_is_present",
      "terminating_state_status": "successful",
      "fi_lookup_key": "columbiacu",
      "is_expected_failure": false,
      "unrestricted": true,
      "email_sent": false,
      "account_linked_on": null,
      "job_ready_on": null,
      "job_created_on": null,
      "completed_on": "2022-06-26T21:36:32.816Z",
      "created_on": "2022-06-26T21:36:32.952Z",
      "last_updated_on": null,
      "_instance": "digital-onboarding"
    },
    {
      "id": 7210,
      "merchant_site_hostname": "amazon.com",
      "meta_key": null,
      "fi_name": "Financial Access FCU",
      "bank_identification_number": null,
      "cuid": "1nlls8ws8gjhh7ey1wh3",
      "par": null,
      "card_customer_key": null,
      "account_customer_key": "12$1nlls8ws8gjhh7ey1wh3",
      "status": "ABANDONED_QUICKSTART",
      "status_message": null,
      "termination_type": "NEVER_STARTED",
      "custom_data": {
        "digital_onboarding": {
          "team_id": "1e2106cd-a588-4238-ad25-2d55e41c18db",
          "contact_id": "609869dc-1c12-4034-91b1-5f4d77678388",
          "page_id": "d9a5eb30-c87f-4351-8df0-cf3f498f6202",
          "journey_id": "7a579eed-78ca-46c0-85a5-267899811da8",
          "slug": "rJAJIz2e5"
        }
      },
      "source": null,
      "time_elapsed": 554244,
      "first_6": null,
      "first_7": null,
      "first_8": null,
      "card_type": null,
      "trace": "{\"key\":\"1nlls8ws8gjhh7ey1wh3\"}",
      "place_card_on_single_site_job_id": 7078,
      "financial_institution_id": 63,
      "merchant_site_id": 12,
      "agent_session_id": null,
      "bin_id": null,
      "html": null,
      "queue_name": "vbs_lambda_queue",
      "job_type": "rpa:rpa",
      "recording_path": null,
      "terminating_state": "wait_for_quick_start_credentials",
      "terminating_state_status": "abandoned_quickstart",
      "fi_lookup_key": "fafcu",
      "is_expected_failure": false,
      "unrestricted": true,
      "email_sent": false,
      "account_linked_on": null,
      "job_ready_on": null,
      "job_created_on": null,
      "completed_on": "2022-06-26T22:42:08.451Z",
      "created_on": "2022-06-26T22:42:08.576Z",
      "last_updated_on": null,
      "_instance": "digital-onboarding"
    }
  ]
}