{
  "date": "2024-01-12",
  "placements": [
    {
      "id": 21646,
      "merchant_site_hostname": "airbnb.com",
      "meta_key": "KM8051649",
      "fi_name": "Elevations Credit Union",
      "bank_identification_number": "40756300",
      "cuid": "0ev13gm713w6vs0axxjo",
      "par": "C7Bt/Djg8RTQjlc5feijKPQEclFE=",
      "card_customer_key": "C7Bt/Djg8RTQjlc5feijKPQEclFE=",
      "account_customer_key": "88$0ev13gm713w6vs0axxjo",
      "status": "CARD_FORM_FAILED",
      "status_message": "Failed to submit your card information.",
      "termination_type": "SITE_INTERACTION_FAILURE",
      "custom_data": null,
      "source": null,
      "time_elapsed": 276644,
      "first_6": "b08c5aa082ef6d8f28ece61e3fb00f06",
      "first_7": "1d6e8b0b368548d366eaad8416776960",
      "first_8": "a59e01a6abd7da0afeb34e05fcad536b",
      "card_type": null,
      "trace": "{\"key\":\"0ev13gm713w6vs0axxjo\"}",
      "place_card_on_single_site_job_id": 21026,
      "financial_institution_id": 199,
      "merchant_site_id": 88,
      "agent_session_id": null,
      "bin_id": 57790,
      "html": null,
      "queue_name": "vbs_lambda_queue",
      "job_type": "rpa:rpa",
      "recording_path": null,
      "terminating_state": null,
      "terminating_state_status": null,
      "fi_lookup_key": "elevationscu",
      "is_expected_failure": false,
      "unrestricted": true,
      "email_sent": false,
      "account_linked_on": "2024-01-12T02:21:14.355Z",
      "job_ready_on": null,
      "job_created_on": null,
      "completed_on": "2024-01-12T02:22:25.611Z",
      "created_on": "2024-01-12T02:22:25.660Z",
      "last_updated_on": null,
      "_instance": "ss01"
    },
    {
      "id": 21647,
      "merchant_site_hostname": "amazon.com",
      "meta_key": "KM8051649",
      "fi_name": "Elevations Credit Union",
      "bank_identification_number": "40756300",
      "cuid": "0ev13gm713w6vs0axxjo",
      "par": "C7Bt/Djg8RTQjlc5feijKPQEclFE=",
      "card_customer_key": "C7Bt/Djg8RTQjlc5feijKPQEclFE=",
      "account_customer_key": "12$0ev13gm713w6vs0axxjo",
      "status": "TIMEOUT_TFA",
      "status_message": "Unable to automatically update your card due to invalid or missing two-factor authentication.",
      "termination_type": "USER_DATA_FAILURE",
      "custom_data": null,
      "source": null,
      "time_elapsed": null,
      "first_6": "b08c5aa082ef6d8f28ece61e3fb00f06",
      "first_7": "1d6e8b0b368548d366eaad8416776960",
      "first_8": "a59e01a6abd7da0afeb34e05fcad536b",
      "card_type": null,
      "trace": null,
      "place_card_on_single_site_job_id": 21027,
      "financial_institution_id": 199,
      "merchant_site_id": 12,
      "agent_session_id": null,
      "bin_id": 57790,
      "html": null,
      "queue_name": "vbs_lambda_queue",
      "job_type": "rpa:rpa",
      "recording_path": null,
      "terminating_state": null,
      "terminating_state_status": null,
      "fi_lookup_key": "elevationscu",
      "is_expected_failure": false,
      "unrestricted": true,
      "email_sent": false,
      "account_linked_on": null,
      "job_ready_on": null,
      "job_created_on": null,
      "completed_on": "2024-01-12T02:24:09.837Z",
      "created_on": "2024-01-12T02:24:09.837Z",
      "last_updated_on": null,
      "_instance": "ss01"
    },
    {
      "id": 21648,
      "merchant_site_hostname": "wsj.com",
      "meta_key": "KM8051649",
      "fi_name": "Elevations Credit Union",
      "bank_identification_number": "40756300",
      "cuid": "0ev13gm713w6vs0axxjo",
      "par": "C7Bt/Djg8RTQjlc5feijKPQEclFE=",
      "card_customer_key": "C7Bt/Djg8RTQjlc5feijKPQEclFE=",
      "account_customer_key": "233$0ev13gm713w6vs0axxjo",
      "status": "SUCCESSFUL",
      "status_message": "Your card was placed successfully.",
      "termination_type": "BILLABLE",
      "custom_data": null,
      "source": null,
      "time_elapsed": 387283,
      "first_6": "b08c5aa082ef6d8f28ece61e3fb00f06",
      "first_7": "1d6e8b0b368548d366eaad8416776960",
      "first_8": "a59e01a6abd7da0afeb34e05fcad536b",
      "card_type": null,
      "trace": "{\"key\":\"0ev13gm713w6vs0axxjo\"}",
      "place_card_on_single_site_job_id": 21025,
      "financial_institution_id": 199,
      "merchant_site_id": 233,
      "agent_session_id": null,
      "bin_id": 57790,
      "html": null,
      "queue_name": "vbs_lambda_queue",
      "job_type": "rpa:rpa",
      "recording_path": null,
      "terminating_state": null,
      "terminating_state_status": null,
      "fi_lookup_key": "elevationscu",
      "is_expected_failure": false,
      "unrestricted": true,
      "email_sent": false,
      "account_linked_on": "2024-01-12T02:23:03.585Z",
      "job_ready_on": null,
      "job_created_on": null,
      "completed_on": "2024-01-12T02:24:19.086Z",
      "created_on": "2024-01-12T02:24:19.142Z",
      "last_updated_on": null,
      "_instance": "ss01"
    },
    {
      "id": 21649,
      "merchant_site_hostname": "verizon.com",
      "meta_key": "MH8050470",
      "fi_name": "Elevations Credit Union",
      "bank_identification_number": "45232900",
      "cuid": "05ynyz7771yxn8cvw3m3",
      "par": "Cc/CWYMLl054UiomqgvOJCw4RrGg=",
      "card_customer_key": "Cc/CWYMLl054UiomqgvOJCw4RrGg=",
      "account_customer_key": "145$05ynyz7771yxn8cvw3m3",
      "status": "CANCELLED",
      "status_message": null,
      "termination_type": "NEVER_STARTED",
      "custom_data": null,
      "source": null,
      "time_elapsed": null,
      "first_6": "5e990d9b6799eb636fbb8ef3b5ca7a09",
      "first_7": "d88c2c4a85712e4a8042b6911fc67c17",
      "first_8": "70246b7da04cf20da4dbc24427897a69",
      "card_type": null,
      "trace": null,
      "place_card_on_single_site_job_id": 21028,
      "financial_institution_id": 199,
      "merchant_site_id": 145,
      "agent_session_id": null,
      "bin_id": 57787,
      "html": null,
      "queue_name": "vbs_lambda_queue",
      "job_type": "rpa:rpa",
      "recording_path": null,
      "terminating_state": null,
      "terminating_state_status": null,
      "fi_lookup_key": "elevationscu",
      "is_expected_failure": false,
      "unrestricted": true,
      "email_sent": false,
      "account_linked_on": null,
      "job_ready_on": null,
      "job_created_on": null,
      "completed_on": "2024-01-12T18:16:07.023Z",
      "created_on": "2024-01-12T18:16:07.023Z",
      "last_updated_on": null,
      "_instance": "ss01"
    },
    {
      "id": 21650,
      "merchant_site_hostname": "siriusxm.com",
      "meta_key": "MH8050470",
      "fi_name": "Elevations Credit Union",
      "bank_identification_number": "45232900",
      "cuid": "05ynyz7771yxn8cvw3m3",
      "par": "Cc/CWYMLl054UiomqgvOJCw4RrGg=",
      "card_customer_key": "Cc/CWYMLl054UiomqgvOJCw4RrGg=",
      "account_customer_key": "53$05ynyz7771yxn8cvw3m3",
      "status": "CANCELLED",
      "status_message": null,
      "termination_type": "NEVER_STARTED",
      "custom_data": null,
      "source": null,
      "time_elapsed": null,
      "first_6": "5e990d9b6799eb636fbb8ef3b5ca7a09",
      "first_7": "d88c2c4a85712e4a8042b6911fc67c17",
      "first_8": "70246b7da04cf20da4dbc24427897a69",
      "card_type": null,
      "trace": null,
      "place_card_on_single_site_job_id": 21029,
      "financial_institution_id": 199,
      "merchant_site_id": 53,
      "agent_session_id": null,
      "bin_id": 57787,
      "html": null,
      "queue_name": "vbs_lambda_queue",
      "job_type": "rpa:rpa",
      "recording_path": null,
      "terminating_state": null,
      "terminating_state_status": null,
      "fi_lookup_key": "elevationscu",
      "is_expected_failure": false,
      "unrestricted": true,
      "email_sent": false,
      "account_linked_on": null,
      "job_ready_on": null,
      "job_created_on": null,
      "completed_on": "2024-01-12T18:16:08.252Z",
      "created_on": "2024-01-12T18:16:08.252Z",
      "last_updated_on": null,
      "_instance": "ss01"
    },
    {
      "id": 21651,
      "merchant_site_hostname": "paypal.com",
      "meta_key": "MH8050470",
      "fi_name": "Elevations Credit Union",
      "bank_identification_number": "45232900",
      "cuid": "05ynyz7771yxn8cvw3m3",
      "par": "Cc/CWYMLl054UiomqgvOJCw4RrGg=",
      "card_customer_key": "Cc/CWYMLl054UiomqgvOJCw4RrGg=",
      "account_customer_key": "20$05ynyz7771yxn8cvw3m3",
      "status": "CANCELLED",
      "status_message": null,
      "termination_type": "NEVER_STARTED",
      "custom_data": null,
      "source": null,
      "time_elapsed": null,
      "first_6": "5e990d9b6799eb636fbb8ef3b5ca7a09",
      "first_7": "d88c2c4a85712e4a8042b6911fc67c17",
      "first_8": "70246b7da04cf20da4dbc24427897a69",
      "card_type": null,
      "trace": null,
      "place_card_on_single_site_job_id": 21030,
      "financial_institution_id": 199,
      "merchant_site_id": 20,
      "agent_session_id": null,
      "bin_id": 57787,
      "html": null,
      "queue_name": "vbs_lambda_queue",
      "job_type": "rpa:rpa",
      "recording_path": null,
      "terminating_state": null,
      "terminating_state_status": null,
      "fi_lookup_key": "elevationscu",
      "is_expected_failure": false,
      "unrestricted": true,
      "email_sent": false,
      "account_linked_on": null,
      "job_ready_on": null,
      "job_created_on": null,
      "completed_on": "2024-01-12T18:16:09.437Z",
      "created_on": "2024-01-12T18:16:09.437Z",
      "last_updated_on": null,
      "_instance": "ss01"
    },
    {
      "id": 21652,
      "merchant_site_hostname": "netflix.com",
      "meta_key": "MH8050470",
      "fi_name": "Elevations Credit Union",
      "bank_identification_number": "45232900",
      "cuid": "05ynyz7771yxn8cvw3m3",
      "par": "Cc/CWYMLl054UiomqgvOJCw4RrGg=",
      "card_customer_key": "Cc/CWYMLl054UiomqgvOJCw4RrGg=",
      "account_customer_key": "40$05ynyz7771yxn8cvw3m3",
      "status": "CANCELLED",
      "status_message": null,
      "termination_type": "NEVER_STARTED",
      "custom_data": null,
      "source": null,
      "time_elapsed": null,
      "first_6": "5e990d9b6799eb636fbb8ef3b5ca7a09",
      "first_7": "d88c2c4a85712e4a8042b6911fc67c17",
      "first_8": "70246b7da04cf20da4dbc24427897a69",
      "card_type": null,
      "trace": null,
      "place_card_on_single_site_job_id": 21031,
      "financial_institution_id": 199,
      "merchant_site_id": 40,
      "agent_session_id": null,
      "bin_id": 57787,
      "html": null,
      "queue_name": "vbs_lambda_queue",
      "job_type": "rpa:rpa",
      "recording_path": null,
      "terminating_state": null,
      "terminating_state_status": null,
      "fi_lookup_key": "elevationscu",
      "is_expected_failure": false,
      "unrestricted": true,
      "email_sent": false,
      "account_linked_on": null,
      "job_ready_on": null,
      "job_created_on": null,
      "completed_on": "2024-01-12T18:16:10.278Z",
      "created_on": "2024-01-12T18:16:10.278Z",
      "last_updated_on": null,
      "_instance": "ss01"
    },
    {
      "id": 21653,
      "merchant_site_hostname": "amazon.com",
      "meta_key": "MH8050470",
      "fi_name": "Elevations Credit Union",
      "bank_identification_number": "45232900",
      "cuid": "05ynyz7771yxn8cvw3m3",
      "par": "Cc/CWYMLl054UiomqgvOJCw4RrGg=",
      "card_customer_key": "Cc/CWYMLl054UiomqgvOJCw4RrGg=",
      "account_customer_key": "12$05ynyz7771yxn8cvw3m3",
      "status": "CANCELLED",
      "status_message": null,
      "termination_type": "NEVER_STARTED",
      "custom_data": null,
      "source": null,
      "time_elapsed": null,
      "first_6": "5e990d9b6799eb636fbb8ef3b5ca7a09",
      "first_7": "d88c2c4a85712e4a8042b6911fc67c17",
      "first_8": "70246b7da04cf20da4dbc24427897a69",
      "card_type": null,
      "trace": null,
      "place_card_on_single_site_job_id": 21032,
      "financial_institution_id": 199,
      "merchant_site_id": 12,
      "agent_session_id": null,
      "bin_id": 57787,
      "html": null,
      "queue_name": "vbs_lambda_queue",
      "job_type": "rpa:rpa",
      "recording_path": null,
      "terminating_state": null,
      "terminating_state_status": null,
      "fi_lookup_key": "elevationscu",
      "is_expected_failure": false,
      "unrestricted": true,
      "email_sent": false,
      "account_linked_on": null,
      "job_ready_on": null,
      "job_created_on": null,
      "completed_on": "2024-01-12T18:16:10.975Z",
      "created_on": "2024-01-12T18:16:10.975Z",
      "last_updated_on": null,
      "_instance": "ss01"
    },
    {
      "id": 21654,
      "merchant_site_hostname": "paypal.com",
      "meta_key": "MH8050470",
      "fi_name": "Elevations Credit Union",
      "bank_identification_number": "45232900",
      "cuid": "05ynyz7771yxn8cvw3m3",
      "par": "Cc/CWYMLl054UiomqgvOJCw4RrGg=",
      "card_customer_key": "Cc/CWYMLl054UiomqgvOJCw4RrGg=",
      "account_customer_key": "20$05ynyz7771yxn8cvw3m3",
      "status": "ABANDONED_QUICKSTART",
      "status_message": null,
      "termination_type": "NEVER_STARTED",
      "custom_data": null,
      "source": null,
      "time_elapsed": 323744,
      "first_6": "5e990d9b6799eb636fbb8ef3b5ca7a09",
      "first_7": "d88c2c4a85712e4a8042b6911fc67c17",
      "first_8": "70246b7da04cf20da4dbc24427897a69",
      "card_type": null,
      "trace": "{\"key\":\"05ynyz7771yxn8cvw3m3\"}",
      "place_card_on_single_site_job_id": 21030,
      "financial_institution_id": 199,
      "merchant_site_id": 20,
      "agent_session_id": null,
      "bin_id": 57787,
      "html": null,
      "queue_name": "vbs_lambda_queue",
      "job_type": "rpa:rpa",
      "recording_path": null,
      "terminating_state": null,
      "terminating_state_status": null,
      "fi_lookup_key": "elevationscu",
      "is_expected_failure": false,
      "unrestricted": true,
      "email_sent": false,
      "account_linked_on": null,
      "job_ready_on": null,
      "job_created_on": null,
      "completed_on": "2024-01-12T18:21:28.071Z",
      "created_on": "2024-01-12T18:21:28.524Z",
      "last_updated_on": null,
      "_instance": "ss01"
    },
    {
      "id": 21655,
      "merchant_site_hostname": "verizon.com",
      "meta_key": "MH8050470",
      "fi_name": "Elevations Credit Union",
      "bank_identification_number": "45232900",
      "cuid": "05ynyz7771yxn8cvw3m3",
      "par": "Cc/CWYMLl054UiomqgvOJCw4RrGg=",
      "card_customer_key": "Cc/CWYMLl054UiomqgvOJCw4RrGg=",
      "account_customer_key": "145$05ynyz7771yxn8cvw3m3",
      "status": "ABANDONED_QUICKSTART",
      "status_message": null,
      "termination_type": "NEVER_STARTED",
      "custom_data": null,
      "source": null,
      "time_elapsed": 330386,
      "first_6": "5e990d9b6799eb636fbb8ef3b5ca7a09",
      "first_7": "d88c2c4a85712e4a8042b6911fc67c17",
      "first_8": "70246b7da04cf20da4dbc24427897a69",
      "card_type": null,
      "trace": "{\"key\":\"05ynyz7771yxn8cvw3m3\"}",
      "place_card_on_single_site_job_id": 21028,
      "financial_institution_id": 199,
      "merchant_site_id": 145,
      "agent_session_id": null,
      "bin_id": 57787,
      "html": null,
      "queue_name": "vbs_lambda_queue",
      "job_type": "rpa:rpa",
      "recording_path": null,
      "terminating_state": null,
      "terminating_state_status": null,
      "fi_lookup_key": "elevationscu",
      "is_expected_failure": false,
      "unrestricted": true,
      "email_sent": false,
      "account_linked_on": null,
      "job_ready_on": null,
      "job_created_on": null,
      "completed_on": "2024-01-12T18:21:32.238Z",
      "created_on": "2024-01-12T18:21:32.342Z",
      "last_updated_on": null,
      "_instance": "ss01"
    },
    {
      "id": 21656,
      "merchant_site_hostname": "amazon.com",
      "meta_key": "MH8050470",
      "fi_name": "Elevations Credit Union",
      "bank_identification_number": "45232900",
      "cuid": "05ynyz7771yxn8cvw3m3",
      "par": "Cc/CWYMLl054UiomqgvOJCw4RrGg=",
      "card_customer_key": "Cc/CWYMLl054UiomqgvOJCw4RrGg=",
      "account_customer_key": "12$05ynyz7771yxn8cvw3m3",
      "status": "ABANDONED_QUICKSTART",
      "status_message": null,
      "termination_type": "NEVER_STARTED",
      "custom_data": null,
      "source": null,
      "time_elapsed": 330221,
      "first_6": "5e990d9b6799eb636fbb8ef3b5ca7a09",
      "first_7": "d88c2c4a85712e4a8042b6911fc67c17",
      "first_8": "70246b7da04cf20da4dbc24427897a69",
      "card_type": null,
      "trace": "{\"key\":\"05ynyz7771yxn8cvw3m3\"}",
      "place_card_on_single_site_job_id": 21032,
      "financial_institution_id": 199,
      "merchant_site_id": 12,
      "agent_session_id": null,
      "bin_id": 57787,
      "html": null,
      "queue_name": "vbs_lambda_queue",
      "job_type": "rpa:rpa",
      "recording_path": null,
      "terminating_state": null,
      "terminating_state_status": null,
      "fi_lookup_key": "elevationscu",
      "is_expected_failure": false,
      "unrestricted": true,
      "email_sent": false,
      "account_linked_on": null,
      "job_ready_on": null,
      "job_created_on": null,
      "completed_on": "2024-01-12T18:21:33.351Z",
      "created_on": "2024-01-12T18:21:33.734Z",
      "last_updated_on": null,
      "_instance": "ss01"
    },
    {
      "id": 21657,
      "merchant_site_hostname": "siriusxm.com",
      "meta_key": "MH8050470",
      "fi_name": "Elevations Credit Union",
      "bank_identification_number": "45232900",
      "cuid": "05ynyz7771yxn8cvw3m3",
      "par": "Cc/CWYMLl054UiomqgvOJCw4RrGg=",
      "card_customer_key": "Cc/CWYMLl054UiomqgvOJCw4RrGg=",
      "account_customer_key": "53$05ynyz7771yxn8cvw3m3",
      "status": "ABANDONED_QUICKSTART",
      "status_message": null,
      "termination_type": "NEVER_STARTED",
      "custom_data": null,
      "source": null,
      "time_elapsed": 334542,
      "first_6": "5e990d9b6799eb636fbb8ef3b5ca7a09",
      "first_7": "d88c2c4a85712e4a8042b6911fc67c17",
      "first_8": "70246b7da04cf20da4dbc24427897a69",
      "card_type": null,
      "trace": "{\"key\":\"05ynyz7771yxn8cvw3m3\"}",
      "place_card_on_single_site_job_id": 21029,
      "financial_institution_id": 199,
      "merchant_site_id": 53,
      "agent_session_id": null,
      "bin_id": 57787,
      "html": null,
      "queue_name": "vbs_lambda_queue",
      "job_type": "rpa:rpa",
      "recording_path": null,
      "terminating_state": null,
      "terminating_state_status": null,
      "fi_lookup_key": "elevationscu",
      "is_expected_failure": false,
      "unrestricted": true,
      "email_sent": false,
      "account_linked_on": null,
      "job_ready_on": null,
      "job_created_on": null,
      "completed_on": "2024-01-12T18:21:33.711Z",
      "created_on": "2024-01-12T18:21:33.853Z",
      "last_updated_on": null,
      "_instance": "ss01"
    },
    {
      "id": 21658,
      "merchant_site_hostname": "netflix.com",
      "meta_key": "MH8050470",
      "fi_name": "Elevations Credit Union",
      "bank_identification_number": "45232900",
      "cuid": "05ynyz7771yxn8cvw3m3",
      "par": "Cc/CWYMLl054UiomqgvOJCw4RrGg=",
      "card_customer_key": "Cc/CWYMLl054UiomqgvOJCw4RrGg=",
      "account_customer_key": "40$05ynyz7771yxn8cvw3m3",
      "status": "ABANDONED_QUICKSTART",
      "status_message": null,
      "termination_type": "NEVER_STARTED",
      "custom_data": null,
      "source": null,
      "time_elapsed": 333966,
      "first_6": "5e990d9b6799eb636fbb8ef3b5ca7a09",
      "first_7": "d88c2c4a85712e4a8042b6911fc67c17",
      "first_8": "70246b7da04cf20da4dbc24427897a69",
      "card_type": null,
      "trace": "{\"key\":\"05ynyz7771yxn8cvw3m3\"}",
      "place_card_on_single_site_job_id": 21031,
      "financial_institution_id": 199,
      "merchant_site_id": 40,
      "agent_session_id": null,
      "bin_id": 57787,
      "html": null,
      "queue_name": "vbs_lambda_queue",
      "job_type": "rpa:rpa",
      "recording_path": null,
      "terminating_state": null,
      "terminating_state_status": null,
      "fi_lookup_key": "elevationscu",
      "is_expected_failure": false,
      "unrestricted": true,
      "email_sent": false,
      "account_linked_on": null,
      "job_ready_on": null,
      "job_created_on": null,
      "completed_on": "2024-01-12T18:21:34.527Z",
      "created_on": "2024-01-12T18:21:34.598Z",
      "last_updated_on": null,
      "_instance": "ss01"
    },
    {
      "id": 18140,
      "merchant_site_hostname": "ups.com",
      "meta_key": "SB7759046",
      "fi_name": "AMOCO Federal Credit Union",
      "bank_identification_number": "523694",
      "cuid": "deh17h7bvsuh8oewozd8",
      "par": "Cny1lDWi0sH7vuZV0WneTpwwu2Io=",
      "card_customer_key": "Cny1lDWi0sH7vuZV0WneTpwwu2Io=",
      "account_customer_key": "143$deh17h7bvsuh8oewozd8",
      "status": "TOO_MANY_LOGIN_FAILURES",
      "status_message": "Unable to automatically update your card due to invalid username/password.",
      "termination_type": "USER_DATA_FAILURE",
      "custom_data": {
        "digital_onboarding": {
          "team_id": "7605df80-0b23-44bd-b625-f2c1aac9246f",
          "contact_id": "454cb75d-ebc3-4d2f-87bb-ffd259c9896a",
          "page_id": "736797ab-28f0-4b26-b2b8-2bfcc7e4892d",
          "journey_id": "94be46f6-a8ed-4e37-b767-866e480ab1a3",
          "slug": "SkgKpEWH3"
        }
      },
      "source": null,
      "time_elapsed": 131463,
      "first_6": "1a8951f702a3d33ff38b5429b381578b",
      "first_7": "00a4c972d4da2511d98bd31dc49355c9",
      "first_8": "ae35611c7ce091f871a63e852f7c2985",
      "card_type": null,
      "trace": "{\"key\":\"deh17h7bvsuh8oewozd8\"}",
      "place_card_on_single_site_job_id": 17525,
      "financial_institution_id": 174,
      "merchant_site_id": 143,
      "agent_session_id": null,
      "bin_id": 573,
      "html": null,
      "queue_name": "vbs_lambda_queue",
      "job_type": "rpa:rpa",
      "recording_path": null,
      "terminating_state": null,
      "terminating_state_status": null,
      "fi_lookup_key": "amocofcu",
      "is_expected_failure": false,
      "unrestricted": true,
      "email_sent": false,
      "account_linked_on": null,
      "job_ready_on": null,
      "job_created_on": null,
      "completed_on": "2024-01-12T13:16:45.675Z",
      "created_on": "2024-01-12T13:16:45.741Z",
      "last_updated_on": null,
      "_instance": "digital-onboarding"
    },
    {
      "id": 18141,
      "merchant_site_hostname": "amazon.com",
      "meta_key": "SB7759046",
      "fi_name": "AMOCO Federal Credit Union",
      "bank_identification_number": "523694",
      "cuid": "deh17h7bvsuh8oewozd8",
      "par": "Cny1lDWi0sH7vuZV0WneTpwwu2Io=",
      "card_customer_key": "Cny1lDWi0sH7vuZV0WneTpwwu2Io=",
      "account_customer_key": "12$deh17h7bvsuh8oewozd8",
      "status": "TOO_MANY_LOGIN_FAILURES",
      "status_message": "Unable to automatically update your card due to invalid username/password.",
      "termination_type": "USER_DATA_FAILURE",
      "custom_data": {
        "digital_onboarding": {
          "team_id": "7605df80-0b23-44bd-b625-f2c1aac9246f",
          "contact_id": "454cb75d-ebc3-4d2f-87bb-ffd259c9896a",
          "page_id": "736797ab-28f0-4b26-b2b8-2bfcc7e4892d",
          "journey_id": "94be46f6-a8ed-4e37-b767-866e480ab1a3",
          "slug": "SkgKpEWH3"
        }
      },
      "source": null,
      "time_elapsed": 164568,
      "first_6": "1a8951f702a3d33ff38b5429b381578b",
      "first_7": "00a4c972d4da2511d98bd31dc49355c9",
      "first_8": "ae35611c7ce091f871a63e852f7c2985",
      "card_type": null,
      "trace": "{\"key\":\"deh17h7bvsuh8oewozd8\"}",
      "place_card_on_single_site_job_id": 17526,
      "financial_institution_id": 174,
      "merchant_site_id": 12,
      "agent_session_id": null,
      "bin_id": 573,
      "html": null,
      "queue_name": "vbs_lambda_queue",
      "job_type": "rpa:rpa",
      "recording_path": null,
      "terminating_state": null,
      "terminating_state_status": null,
      "fi_lookup_key": "amocofcu",
      "is_expected_failure": false,
      "unrestricted": true,
      "email_sent": false,
      "account_linked_on": null,
      "job_ready_on": null,
      "job_created_on": null,
      "completed_on": "2024-01-12T13:17:13.090Z",
      "created_on": "2024-01-12T13:17:13.157Z",
      "last_updated_on": null,
      "_instance": "digital-onboarding"
    },
    {
      "id": 18142,
      "merchant_site_hostname": "lowes.com",
      "meta_key": "SB7759046",
      "fi_name": "AMOCO Federal Credit Union",
      "bank_identification_number": "523694",
      "cuid": "deh17h7bvsuh8oewozd8",
      "par": "Cny1lDWi0sH7vuZV0WneTpwwu2Io=",
      "card_customer_key": "Cny1lDWi0sH7vuZV0WneTpwwu2Io=",
      "account_customer_key": "51$deh17h7bvsuh8oewozd8",
      "status": "UNSUCCESSFUL",
      "status_message": "Unable to automatically update your card on this site.",
      "termination_type": "SITE_INTERACTION_FAILURE",
      "custom_data": {
        "digital_onboarding": {
          "team_id": "7605df80-0b23-44bd-b625-f2c1aac9246f",
          "contact_id": "454cb75d-ebc3-4d2f-87bb-ffd259c9896a",
          "page_id": "736797ab-28f0-4b26-b2b8-2bfcc7e4892d",
          "journey_id": "94be46f6-a8ed-4e37-b767-866e480ab1a3",
          "slug": "SkgKpEWH3"
        }
      },
      "source": null,
      "time_elapsed": 257494,
      "first_6": "1a8951f702a3d33ff38b5429b381578b",
      "first_7": "00a4c972d4da2511d98bd31dc49355c9",
      "first_8": "ae35611c7ce091f871a63e852f7c2985",
      "card_type": null,
      "trace": "{\"key\":\"deh17h7bvsuh8oewozd8\"}",
      "place_card_on_single_site_job_id": 17529,
      "financial_institution_id": 174,
      "merchant_site_id": 51,
      "agent_session_id": null,
      "bin_id": 573,
      "html": null,
      "queue_name": "vbs_lambda_queue",
      "job_type": "rpa:rpa",
      "recording_path": null,
      "terminating_state": null,
      "terminating_state_status": null,
      "fi_lookup_key": "amocofcu",
      "is_expected_failure": false,
      "unrestricted": true,
      "email_sent": false,
      "account_linked_on": "2024-01-12T13:18:04.038Z",
      "job_ready_on": null,
      "job_created_on": null,
      "completed_on": "2024-01-12T13:18:55.481Z",
      "created_on": "2024-01-12T13:18:55.557Z",
      "last_updated_on": null,
      "_instance": "digital-onboarding"
    },
    {
      "id": 18143,
      "merchant_site_hostname": "oldnavy.com",
      "meta_key": "SB7759046",
      "fi_name": "AMOCO Federal Credit Union",
      "bank_identification_number": "523694",
      "cuid": "deh17h7bvsuh8oewozd8",
      "par": "Cny1lDWi0sH7vuZV0WneTpwwu2Io=",
      "card_customer_key": "Cny1lDWi0sH7vuZV0WneTpwwu2Io=",
      "account_customer_key": "95$deh17h7bvsuh8oewozd8",
      "status": "ABANDONED_QUICKSTART",
      "status_message": null,
      "termination_type": "NEVER_STARTED",
      "custom_data": {
        "digital_onboarding": {
          "team_id": "7605df80-0b23-44bd-b625-f2c1aac9246f",
          "contact_id": "454cb75d-ebc3-4d2f-87bb-ffd259c9896a",
          "page_id": "736797ab-28f0-4b26-b2b8-2bfcc7e4892d",
          "journey_id": "94be46f6-a8ed-4e37-b767-866e480ab1a3",
          "slug": "SkgKpEWH3"
        }
      },
      "source": null,
      "time_elapsed": 329602,
      "first_6": "1a8951f702a3d33ff38b5429b381578b",
      "first_7": "00a4c972d4da2511d98bd31dc49355c9",
      "first_8": "ae35611c7ce091f871a63e852f7c2985",
      "card_type": null,
      "trace": "{\"key\":\"deh17h7bvsuh8oewozd8\"}",
      "place_card_on_single_site_job_id": 17527,
      "financial_institution_id": 174,
      "merchant_site_id": 95,
      "agent_session_id": null,
      "bin_id": 573,
      "html": null,
      "queue_name": "vbs_lambda_queue",
      "job_type": "rpa:rpa",
      "recording_path": null,
      "terminating_state": null,
      "terminating_state_status": null,
      "fi_lookup_key": "amocofcu",
      "is_expected_failure": false,
      "unrestricted": true,
      "email_sent": false,
      "account_linked_on": null,
      "job_ready_on": null,
      "job_created_on": null,
      "completed_on": "2024-01-12T13:19:59.462Z",
      "created_on": "2024-01-12T13:19:59.543Z",
      "last_updated_on": null,
      "_instance": "digital-onboarding"
    },
    {
      "id": 18144,
      "merchant_site_hostname": "kroger.com",
      "meta_key": "SB7759046",
      "fi_name": "AMOCO Federal Credit Union",
      "bank_identification_number": "523694",
      "cuid": "deh17h7bvsuh8oewozd8",
      "par": "Cny1lDWi0sH7vuZV0WneTpwwu2Io=",
      "card_customer_key": "Cny1lDWi0sH7vuZV0WneTpwwu2Io=",
      "account_customer_key": "6$deh17h7bvsuh8oewozd8",
      "status": "ABANDONED_QUICKSTART",
      "status_message": null,
      "termination_type": "NEVER_STARTED",
      "custom_data": {
        "digital_onboarding": {
          "team_id": "7605df80-0b23-44bd-b625-f2c1aac9246f",
          "contact_id": "454cb75d-ebc3-4d2f-87bb-ffd259c9896a",
          "page_id": "736797ab-28f0-4b26-b2b8-2bfcc7e4892d",
          "journey_id": "94be46f6-a8ed-4e37-b767-866e480ab1a3",
          "slug": "SkgKpEWH3"
        }
      },
      "source": null,
      "time_elapsed": 373456,
      "first_6": "1a8951f702a3d33ff38b5429b381578b",
      "first_7": "00a4c972d4da2511d98bd31dc49355c9",
      "first_8": "ae35611c7ce091f871a63e852f7c2985",
      "card_type": null,
      "trace": "{\"key\":\"deh17h7bvsuh8oewozd8\"}",
      "place_card_on_single_site_job_id": 17528,
      "financial_institution_id": 174,
      "merchant_site_id": 6,
      "agent_session_id": null,
      "bin_id": 573,
      "html": null,
      "queue_name": "vbs_lambda_queue",
      "job_type": "rpa:rpa",
      "recording_path": null,
      "terminating_state": null,
      "terminating_state_status": null,
      "fi_lookup_key": "amocofcu",
      "is_expected_failure": false,
      "unrestricted": true,
      "email_sent": false,
      "account_linked_on": null,
      "job_ready_on": null,
      "job_created_on": null,
      "completed_on": "2024-01-12T13:20:49.337Z",
      "created_on": "2024-01-12T13:20:49.639Z",
      "last_updated_on": null,
      "_instance": "digital-onboarding"
    }
  ]
}