{
  "date": "2024-10-15",
  "sessions": [
    {
      "id": 6906,
      "cuid": "dt08q6xhcjbw2f3zvirk",
      "source": null,
      "successful_jobs": 0,
      "failed_jobs": 0,
      "total_jobs": 0,
      "agent_session_id": "0d06805b-b568-4a34-bdce-d01d8ff602ed",
      "cardholder_id": null,
      "financial_institution_id": 168,
      "financial_institution_lookup_key": "trueccu",
      "clickstream": null,
      "closed_on": "2024-10-15T00:40:44.926Z",
      "custom_data": null,
      "created_on": "2024-10-15T00:24:35.203Z",
      "last_updated_on": "2024-10-15T00:40:44.927Z",
      "_instance": "ss01"
    },
    {
      "id": 6907,
      "cuid": "6vhgm5vga5qj8q0f9m21",
      "source": null,
      "successful_jobs": 0,
      "failed_jobs": 0,
      "total_jobs": 0,
      "agent_session_id": "efa33dcf-4ef2-4f8a-b786-47882581ecb8",
      "cardholder_id": null,
      "financial_institution_id": 168,
      "financial_institution_lookup_key": "trueccu",
      "clickstream": null,
      "closed_on": "2024-10-15T09:55:44.855Z",
      "custom_data": null,
      "created_on": "2024-10-15T09:38:35.558Z",
      "last_updated_on": "2024-10-15T09:55:44.857Z",
      "_instance": "ss01"
    },
    {
      "id": 6908,
      "cuid": "3s45hyz2e9xlysrexplk",
      "source": null,
      "successful_jobs": 0,
      "failed_jobs": 0,
      "total_jobs": 0,
      "agent_session_id": "6cd17bfb-4877-471a-852d-0a42b127f4df",
      "cardholder_id": null,
      "financial_institution_id": 172,
      "financial_institution_lookup_key": "premieronecu",
      "clickstream": null,
      "closed_on": "2024-10-15T11:25:44.848Z",
      "custom_data": null,
      "created_on": "2024-10-15T11:07:01.295Z",
      "last_updated_on": "2024-10-15T11:25:44.947Z",
      "_instance": "ss01"
    },
    {
      "id": 6909,
      "cuid": "jq1ovyjebzdtzdi9izwt",
      "source": null,
      "successful_jobs": 0,
      "failed_jobs": 0,
      "total_jobs": 0,
      "agent_session_id": "e3e1b618-ab44-4d3a-ac57-6917c27fcd10",
      "cardholder_id": null,
      "financial_institution_id": 172,
      "financial_institution_lookup_key": "premieronecu",
      "clickstream": null,
      "closed_on": "2024-10-15T11:30:44.866Z",
      "custom_data": null,
      "created_on": "2024-10-15T11:11:40.521Z",
      "last_updated_on": "2024-10-15T11:30:44.868Z",
      "_instance": "ss01"
    },
    {
      "id": 6910,
      "cuid": "phtdlnlbj95k1j0ajuhe",
      "source": null,
      "successful_jobs": 0,
      "failed_jobs": 0,
      "total_jobs": 0,
      "agent_session_id": "9ec08972-f4db-4bcb-8429-f0ec637dd563",
      "cardholder_id": null,
      "financial_institution_id": 168,
      "financial_institution_lookup_key": "trueccu",
      "clickstream": [
        {
          "url": "/select-merchants",
          "timestamp": "2024-10-15T13:22:15.485Z",
          "page_title": "Select Merchants"
        },
        {
          "url": "/user-data-collection",
          "timestamp": "2024-10-15T13:23:18.113Z",
          "page_title": "User Data Collection"
        },
        {
          "url": "/user-data-collection",
          "timestamp": "2024-10-15T13:25:37.077Z",
          "page_title": "User Data Collection"
        }
      ],
      "closed_on": "2024-10-15T13:40:45.602Z",
      "custom_data": null,
      "created_on": "2024-10-15T13:25:35.699Z",
      "last_updated_on": "2024-10-15T13:40:45.629Z",
      "_instance": "ss01"
    },
    {
      "id": 6911,
      "cuid": "ba8q31qi5uvt9br6kmwp",
      "source": null,
      "successful_jobs": 0,
      "failed_jobs": 0,
      "total_jobs": 0,
      "agent_session_id": "f0fb92ec-bd0d-4f22-be0d-f7fa9f4998b5",
      "cardholder_id": null,
      "financial_institution_id": 168,
      "financial_institution_lookup_key": "trueccu",
      "clickstream": null,
      "closed_on": "2024-10-15T13:45:44.834Z",
      "custom_data": null,
      "created_on": "2024-10-15T13:28:10.283Z",
      "last_updated_on": "2024-10-15T13:45:44.839Z",
      "_instance": "ss01"
    },
    {
      "id": 6912,
      "cuid": "01qvivnt3ieng67kmibm",
      "source": null,
      "successful_jobs": 1,
      "failed_jobs": 0,
      "total_jobs": 1,
      "agent_session_id": "66c013e3-ab45-4167-a95b-a6025c184f80",
      "cardholder_id": null,
      "financial_institution_id": 268,
      "financial_institution_lookup_key": "bmifcu",
      "clickstream": [
        {
          "url": "/select-merchants",
          "timestamp": "2024-10-15T13:27:46.379Z",
          "page_title": "Select Merchants"
        },
        {
          "url": "/user-data-collection",
          "timestamp": "2024-10-15T13:28:15.941Z",
          "page_title": "User Data Collection"
        },
        {
          "url": "/user-data-collection",
          "timestamp": "2024-10-15T13:29:27.547Z",
          "page_title": "User Data Collection"
        },
        {
          "url": "/credential-entry",
          "timestamp": "2024-10-15T13:29:27.668Z",
          "page_title": "Credential Entry"
        }
      ],
      "closed_on": "2024-10-15T13:50:44.758Z",
      "custom_data": null,
      "created_on": "2024-10-15T13:29:27.144Z",
      "last_updated_on": "2024-10-15T13:50:44.859Z",
      "_instance": "ss01"
    },
    {
      "id": 6913,
      "cuid": "ytj11oi8187kk05nq9gk",
      "source": null,
      "successful_jobs": 0,
      "failed_jobs": 0,
      "total_jobs": 0,
      "agent_session_id": "e09ba285-a9db-4855-bc4c-6e1e35a4bc86",
      "cardholder_id": null,
      "financial_institution_id": 168,
      "financial_institution_lookup_key": "trueccu",
      "clickstream": null,
      "closed_on": "2024-10-15T14:30:45.737Z",
      "custom_data": null,
      "created_on": "2024-10-15T14:11:49.127Z",
      "last_updated_on": "2024-10-15T14:30:45.738Z",
      "_instance": "ss01"
    },
    {
      "id": 6914,
      "cuid": "8084pwbocfk93dykv682",
      "source": null,
      "successful_jobs": 1,
      "failed_jobs": 0,
      "total_jobs": 1,
      "agent_session_id": "b16c005a-b54e-48a2-8c38-6ee477f72802",
      "cardholder_id": null,
      "financial_institution_id": 274,
      "financial_institution_lookup_key": "gatecity",
      "clickstream": [
        {
          "url": "/select-merchants",
          "timestamp": "2024-10-15T14:01:00.538Z",
          "page_title": "Select Merchants"
        },
        {
          "url": "/user-data-collection",
          "timestamp": "2024-10-15T14:11:10.782Z",
          "page_title": "User Data Collection"
        },
        {
          "url": "/user-data-collection",
          "timestamp": "2024-10-15T14:12:31.090Z",
          "page_title": "User Data Collection"
        },
        {
          "url": "/credential-entry",
          "timestamp": "2024-10-15T14:12:31.167Z",
          "page_title": "Credential Entry"
        }
      ],
      "closed_on": "2024-10-15T14:30:45.526Z",
      "custom_data": null,
      "created_on": "2024-10-15T14:12:29.555Z",
      "last_updated_on": "2024-10-15T14:30:45.527Z",
      "_instance": "ss01"
    },
    {
      "id": 6915,
      "cuid": "3ljrr65qeu8c2k8pp7si",
      "source": null,
      "successful_jobs": 0,
      "failed_jobs": 0,
      "total_jobs": 0,
      "agent_session_id": "a5827177-abef-4fa0-ab03-de430166fbce",
      "cardholder_id": null,
      "financial_institution_id": 168,
      "financial_institution_lookup_key": "trueccu",
      "clickstream": null,
      "closed_on": "2024-10-15T14:30:45.735Z",
      "custom_data": null,
      "created_on": "2024-10-15T14:14:22.236Z",
      "last_updated_on": "2024-10-15T14:30:45.737Z",
      "_instance": "ss01"
    },
    {
      "id": 6916,
      "cuid": "j6d9qnk20pt9ie1kzglm",
      "source": null,
      "successful_jobs": 0,
      "failed_jobs": 0,
      "total_jobs": 1,
      "agent_session_id": "ab75ea64-b362-452b-9ab4-41f6ee16592c",
      "cardholder_id": null,
      "financial_institution_id": 274,
      "financial_institution_lookup_key": "gatecity",
      "clickstream": [
        {
          "url": "/select-merchants",
          "timestamp": "2024-10-15T14:01:00.538Z",
          "page_title": "Select Merchants"
        },
        {
          "url": "/user-data-collection",
          "timestamp": "2024-10-15T14:11:10.782Z",
          "page_title": "User Data Collection"
        },
        {
          "url": "/user-data-collection",
          "timestamp": "2024-10-15T14:12:31.090Z",
          "page_title": "User Data Collection"
        },
        {
          "url": "/credential-entry",
          "timestamp": "2024-10-15T14:12:31.167Z",
          "page_title": "Credential Entry"
        },
        {
          "url": "/select-merchants",
          "timestamp": "2024-10-15T14:14:38.849Z",
          "page_title": "Select Merchants"
        },
        {
          "url": "/user-data-collection",
          "timestamp": "2024-10-15T14:16:24.532Z",
          "page_title": "User Data Collection"
        },
        {
          "url": "/credential-entry",
          "timestamp": "2024-10-15T14:16:35.566Z",
          "page_title": "Credential Entry"
        },
        {
          "url": "/credential-entry",
          "timestamp": "2024-10-15T14:16:35.722Z",
          "page_title": "Credential Entry"
        }
      ],
      "closed_on": "2024-10-15T14:35:45.252Z",
      "custom_data": null,
      "created_on": "2024-10-15T14:16:34.142Z",
      "last_updated_on": "2024-10-15T14:35:45.256Z",
      "_instance": "ss01"
    },
    {
      "id": 6917,
      "cuid": "s3ayd0jnkgt7onbh36u1",
      "source": null,
      "successful_jobs": 0,
      "failed_jobs": 0,
      "total_jobs": 1,
      "agent_session_id": "75cdd9a4-40f2-4218-be25-9b6a017ae172",
      "cardholder_id": null,
      "financial_institution_id": 274,
      "financial_institution_lookup_key": "gatecity",
      "clickstream": [
        {
          "url": "/select-merchants",
          "timestamp": "2024-10-15T14:01:00.538Z",
          "page_title": "Select Merchants"
        },
        {
          "url": "/user-data-collection",
          "timestamp": "2024-10-15T14:11:10.782Z",
          "page_title": "User Data Collection"
        },
        {
          "url": "/user-data-collection",
          "timestamp": "2024-10-15T14:12:31.090Z",
          "page_title": "User Data Collection"
        },
        {
          "url": "/credential-entry",
          "timestamp": "2024-10-15T14:12:31.167Z",
          "page_title": "Credential Entry"
        },
        {
          "url": "/select-merchants",
          "timestamp": "2024-10-15T14:14:38.849Z",
          "page_title": "Select Merchants"
        },
        {
          "url": "/user-data-collection",
          "timestamp": "2024-10-15T14:16:24.532Z",
          "page_title": "User Data Collection"
        },
        {
          "url": "/credential-entry",
          "timestamp": "2024-10-15T14:16:35.566Z",
          "page_title": "Credential Entry"
        },
        {
          "url": "/credential-entry",
          "timestamp": "2024-10-15T14:16:35.722Z",
          "page_title": "Credential Entry"
        },
        {
          "url": "/select-merchants",
          "timestamp": "2024-10-15T14:18:30.059Z",
          "page_title": "Select Merchants"
        },
        {
          "url": "/user-data-collection",
          "timestamp": "2024-10-15T14:18:36.975Z",
          "page_title": "User Data Collection"
        },
        {
          "url": "/credential-entry",
          "timestamp": "2024-10-15T14:18:45.380Z",
          "page_title": "Credential Entry"
        }
      ],
      "closed_on": "2024-10-15T14:35:45.464Z",
      "custom_data": null,
      "created_on": "2024-10-15T14:18:43.999Z",
      "last_updated_on": "2024-10-15T14:35:45.567Z",
      "_instance": "ss01"
    },
    {
      "id": 6918,
      "cuid": "7306227zp8ixdizfgagg",
      "source": null,
      "successful_jobs": 1,
      "failed_jobs": 0,
      "total_jobs": 1,
      "agent_session_id": "924db0ad-f68a-4b95-a952-cef9f9ec465b",
      "cardholder_id": null,
      "financial_institution_id": 274,
      "financial_institution_lookup_key": "gatecity",
      "clickstream": [
        {
          "url": "/select-merchants",
          "timestamp": "2024-10-15T14:01:00.538Z",
          "page_title": "Select Merchants"
        },
        {
          "url": "/user-data-collection",
          "timestamp": "2024-10-15T14:11:10.782Z",
          "page_title": "User Data Collection"
        },
        {
          "url": "/user-data-collection",
          "timestamp": "2024-10-15T14:12:31.090Z",
          "page_title": "User Data Collection"
        },
        {
          "url": "/credential-entry",
          "timestamp": "2024-10-15T14:12:31.167Z",
          "page_title": "Credential Entry"
        },
        {
          "url": "/select-merchants",
          "timestamp": "2024-10-15T14:14:38.849Z",
          "page_title": "Select Merchants"
        },
        {
          "url": "/user-data-collection",
          "timestamp": "2024-10-15T14:16:24.532Z",
          "page_title": "User Data Collection"
        },
        {
          "url": "/credential-entry",
          "timestamp": "2024-10-15T14:16:35.566Z",
          "page_title": "Credential Entry"
        },
        {
          "url": "/credential-entry",
          "timestamp": "2024-10-15T14:16:35.722Z",
          "page_title": "Credential Entry"
        },
        {
          "url": "/select-merchants",
          "timestamp": "2024-10-15T14:18:30.059Z",
          "page_title": "Select Merchants"
        },
        {
          "url": "/user-data-collection",
          "timestamp": "2024-10-15T14:18:36.975Z",
          "page_title": "User Data Collection"
        },
        {
          "url": "/credential-entry",
          "timestamp": "2024-10-15T14:18:45.380Z",
          "page_title": "Credential Entry"
        },
        {
          "url": "/select-merchants",
          "timestamp": "2024-10-15T14:20:17.717Z",
          "page_title": "Select Merchants"
        },
        {
          "url": "/user-data-collection",
          "timestamp": "2024-10-15T14:20:34.196Z",
          "page_title": "User Data Collection"
        },
        {
          "url": "/credential-entry",
          "timestamp": "2024-10-15T14:20:42.684Z",
          "page_title": "Credential Entry"
        }
      ],
      "closed_on": "2024-10-15T14:40:45.214Z",
      "custom_data": null,
      "created_on": "2024-10-15T14:20:41.341Z",
      "last_updated_on": "2024-10-15T14:40:45.244Z",
      "_instance": "ss01"
    },
    {
      "id": 6919,
      "cuid": "9co1qi0vd2p69600n6x0",
      "source": null,
      "successful_jobs": 0,
      "failed_jobs": 0,
      "total_jobs": 0,
      "agent_session_id": "86b918ce-fad3-44d2-a1cd-09c2dde0df11",
      "cardholder_id": null,
      "financial_institution_id": 168,
      "financial_institution_lookup_key": "trueccu",
      "clickstream": null,
      "closed_on": "2024-10-15T15:25:44.790Z",
      "custom_data": null,
      "created_on": "2024-10-15T15:10:07.027Z",
      "last_updated_on": "2024-10-15T15:25:44.792Z",
      "_instance": "ss01"
    },
    {
      "id": 6920,
      "cuid": "3g6j10e78adgyd82wisk",
      "source": null,
      "successful_jobs": 0,
      "failed_jobs": 0,
      "total_jobs": 0,
      "agent_session_id": "2a629704-9134-4fdc-9d60-09e5ea12d001",
      "cardholder_id": null,
      "financial_institution_id": 166,
      "financial_institution_lookup_key": "centracu",
      "clickstream": [
        {
          "url": "/select-merchants",
          "timestamp": "2024-10-15T15:22:15.353Z",
          "page_title": "Select Merchants"
        },
        {
          "url": "/user-data-collection",
          "timestamp": "2024-10-15T15:22:50.088Z",
          "page_title": "User Data Collection"
        },
        {
          "url": "/user-data-collection",
          "timestamp": "2024-10-15T15:24:26.330Z",
          "page_title": "User Data Collection"
        },
        {
          "url": "/credential-entry",
          "timestamp": "2024-10-15T15:24:26.623Z",
          "page_title": "Credential Entry"
        }
      ],
      "closed_on": "2024-10-15T15:40:45.138Z",
      "custom_data": null,
      "created_on": "2024-10-15T15:24:25.765Z",
      "last_updated_on": "2024-10-15T15:40:45.143Z",
      "_instance": "ss01"
    },
    {
      "id": 6921,
      "cuid": "qt78fig8m7256g77ub6e",
      "source": null,
      "successful_jobs": 0,
      "failed_jobs": 0,
      "total_jobs": 0,
      "agent_session_id": "40b7e88a-6fa9-41ac-99fb-fd9cc7782419",
      "cardholder_id": null,
      "financial_institution_id": 168,
      "financial_institution_lookup_key": "trueccu",
      "clickstream": null,
      "closed_on": "2024-10-15T15:55:44.835Z",
      "custom_data": null,
      "created_on": "2024-10-15T15:38:39.497Z",
      "last_updated_on": "2024-10-15T15:55:44.836Z",
      "_instance": "ss01"
    },
    {
      "id": 6922,
      "cuid": "81ecs3b9emupp4j0i7nw",
      "source": null,
      "successful_jobs": 0,
      "failed_jobs": 0,
      "total_jobs": 0,
      "agent_session_id": "d1312c21-4bb8-4ea5-ba08-e259df2f0eac",
      "cardholder_id": null,
      "financial_institution_id": 168,
      "financial_institution_lookup_key": "trueccu",
      "clickstream": null,
      "closed_on": "2024-10-15T17:00:45.361Z",
      "custom_data": null,
      "created_on": "2024-10-15T16:41:34.187Z",
      "last_updated_on": "2024-10-15T17:00:45.434Z",
      "_instance": "ss01"
    },
    {
      "id": 6923,
      "cuid": "18mgoce5u3zifudp5opu",
      "source": null,
      "successful_jobs": 0,
      "failed_jobs": 0,
      "total_jobs": 0,
      "agent_session_id": "c1c7c317-ec74-4fad-92d0-e34c397e2e5a",
      "cardholder_id": null,
      "financial_institution_id": 168,
      "financial_institution_lookup_key": "trueccu",
      "clickstream": null,
      "closed_on": "2024-10-15T17:05:44.843Z",
      "custom_data": null,
      "created_on": "2024-10-15T16:48:09.798Z",
      "last_updated_on": "2024-10-15T17:05:44.844Z",
      "_instance": "ss01"
    },
    {
      "id": 6924,
      "cuid": "a7269oktpgj92k56x942",
      "source": null,
      "successful_jobs": 0,
      "failed_jobs": 0,
      "total_jobs": 1,
      "agent_session_id": "167d15fa-297a-4dc9-97be-7451654043e9",
      "cardholder_id": null,
      "financial_institution_id": 133,
      "financial_institution_lookup_key": "loccu",
      "clickstream": [
        {
          "url": "/select-merchants",
          "timestamp": "2024-10-15T17:35:27.983Z",
          "page_title": "Select Merchants"
        },
        {
          "url": "/user-data-collection",
          "timestamp": "2024-10-15T17:35:37.693Z",
          "page_title": "User Data Collection"
        },
        {
          "url": "/user-data-collection",
          "timestamp": "2024-10-15T17:36:32.741Z",
          "page_title": "User Data Collection"
        },
        {
          "url": "/credential-entry",
          "timestamp": "2024-10-15T17:36:32.898Z",
          "page_title": "Credential Entry"
        }
      ],
      "closed_on": "2024-10-15T17:55:44.675Z",
      "custom_data": null,
      "created_on": "2024-10-15T17:36:32.376Z",
      "last_updated_on": "2024-10-15T17:55:44.750Z",
      "_instance": "ss01"
    },
    {
      "id": 6925,
      "cuid": "5en2q3o9istr8wss3rvl",
      "source": null,
      "successful_jobs": 0,
      "failed_jobs": 0,
      "total_jobs": 0,
      "agent_session_id": "3629906e-75f4-44b9-baa6-e11c21cca097",
      "cardholder_id": null,
      "financial_institution_id": 168,
      "financial_institution_lookup_key": "trueccu",
      "clickstream": null,
      "closed_on": "2024-10-15T19:00:44.694Z",
      "custom_data": null,
      "created_on": "2024-10-15T18:42:50.866Z",
      "last_updated_on": "2024-10-15T19:00:44.695Z",
      "_instance": "ss01"
    },
    {
      "id": 6926,
      "cuid": "adaajneuli5xsa1vx13j",
      "source": null,
      "successful_jobs": 0,
      "failed_jobs": 0,
      "total_jobs": 0,
      "agent_session_id": "0e7ae7fd-17b0-4942-aeb9-c32597dd6f79",
      "cardholder_id": null,
      "financial_institution_id": 171,
      "financial_institution_lookup_key": "dupagecu",
      "clickstream": [
        {
          "url": "/select-merchants",
          "timestamp": "2024-10-15T20:13:57.753Z",
          "page_title": "Select Merchants"
        },
        {
          "url": "/user-data-collection",
          "timestamp": "2024-10-15T20:15:31.629Z",
          "page_title": "User Data Collection"
        },
        {
          "url": "/credential-entry",
          "timestamp": "2024-10-15T20:19:09.112Z",
          "page_title": "Credential Entry"
        }
      ],
      "closed_on": "2024-10-15T20:35:44.692Z",
      "custom_data": null,
      "created_on": "2024-10-15T20:19:08.572Z",
      "last_updated_on": "2024-10-15T20:35:44.694Z",
      "_instance": "ss01"
    },
    {
      "id": 6927,
      "cuid": "qkup17zia2k96rvhopyo",
      "source": null,
      "successful_jobs": 0,
      "failed_jobs": 0,
      "total_jobs": 0,
      "agent_session_id": "39feeb9b-e824-4da2-b42e-bcea4ff6f51a",
      "cardholder_id": null,
      "financial_institution_id": 166,
      "financial_institution_lookup_key": "centracu",
      "clickstream": [
        {
          "url": "/select-merchants",
          "timestamp": "2024-10-15T20:34:52.152Z",
          "page_title": "Select Merchants"
        },
        {
          "url": "/user-data-collection",
          "timestamp": "2024-10-15T20:37:14.842Z",
          "page_title": "User Data Collection"
        },
        {
          "url": "/user-data-collection",
          "timestamp": "2024-10-15T20:38:53.448Z",
          "page_title": "User Data Collection"
        },
        {
          "url": "/credential-entry",
          "timestamp": "2024-10-15T20:38:53.666Z",
          "page_title": "Credential Entry"
        }
      ],
      "closed_on": "2024-10-15T20:55:44.759Z",
      "custom_data": null,
      "created_on": "2024-10-15T20:38:52.698Z",
      "last_updated_on": "2024-10-15T20:55:44.764Z",
      "_instance": "ss01"
    },
    {
      "id": 6928,
      "cuid": "yt1l5t469valyyzwku8e",
      "source": null,
      "successful_jobs": 1,
      "failed_jobs": 0,
      "total_jobs": 1,
      "agent_session_id": "6b8409dd-926e-48c4-a3bd-450245ebc5b5",
      "cardholder_id": null,
      "financial_institution_id": 134,
      "financial_institution_lookup_key": "ornlfcu",
      "clickstream": [
        {
          "url": "/select-merchants",
          "timestamp": "2024-10-15T20:39:10.166Z",
          "page_title": "Select Merchants"
        },
        {
          "url": "/user-data-collection",
          "timestamp": "2024-10-15T20:39:24.688Z",
          "page_title": "User Data Collection"
        },
        {
          "url": "/credential-entry",
          "timestamp": "2024-10-15T20:41:44.537Z",
          "page_title": "Credential Entry"
        },
        {
          "url": "/credential-entry",
          "timestamp": "2024-10-15T20:41:44.569Z",
          "page_title": "Credential Entry"
        }
      ],
      "closed_on": "2024-10-15T21:00:44.760Z",
      "custom_data": null,
      "created_on": "2024-10-15T20:41:43.973Z",
      "last_updated_on": "2024-10-15T21:00:44.762Z",
      "_instance": "ss01"
    },
    {
      "id": 6929,
      "cuid": "04dfr93yhqiuvw1wqoim",
      "source": null,
      "successful_jobs": 0,
      "failed_jobs": 0,
      "total_jobs": 0,
      "agent_session_id": "eaa2fd1d-9ba7-4e00-8ecb-ef1461c77152",
      "cardholder_id": null,
      "financial_institution_id": 168,
      "financial_institution_lookup_key": "trueccu",
      "clickstream": null,
      "closed_on": "2024-10-15T21:30:44.873Z",
      "custom_data": null,
      "created_on": "2024-10-15T21:13:42.454Z",
      "last_updated_on": "2024-10-15T21:30:44.875Z",
      "_instance": "ss01"
    },
    {
      "id": 6930,
      "cuid": "8ap5yf41belourxd65ak",
      "source": null,
      "successful_jobs": 0,
      "failed_jobs": 0,
      "total_jobs": 0,
      "agent_session_id": "627cd5ae-846b-45f1-8609-87dd94dd213d",
      "cardholder_id": null,
      "financial_institution_id": 168,
      "financial_institution_lookup_key": "trueccu",
      "clickstream": null,
      "closed_on": "2024-10-15T21:45:45.127Z",
      "custom_data": null,
      "created_on": "2024-10-15T21:29:30.985Z",
      "last_updated_on": "2024-10-15T21:45:45.130Z",
      "_instance": "ss01"
    },
    {
      "id": 6931,
      "cuid": "8r9n47lp93gzuodhofi5",
      "source": null,
      "successful_jobs": 0,
      "failed_jobs": 0,
      "total_jobs": 0,
      "agent_session_id": "a65df20e-5226-4181-bc64-afa40d80f511",
      "cardholder_id": null,
      "financial_institution_id": 168,
      "financial_institution_lookup_key": "trueccu",
      "clickstream": null,
      "closed_on": "2024-10-15T22:00:44.926Z",
      "custom_data": null,
      "created_on": "2024-10-15T21:45:09.228Z",
      "last_updated_on": "2024-10-15T22:00:44.930Z",
      "_instance": "ss01"
    },
    {
      "id": 6932,
      "cuid": "0pm6qbb9n32wureuce6j",
      "source": null,
      "successful_jobs": 0,
      "failed_jobs": 0,
      "total_jobs": 0,
      "agent_session_id": "df96b3e7-67b9-401c-8b97-9d50b0e0246b",
      "cardholder_id": null,
      "financial_institution_id": 168,
      "financial_institution_lookup_key": "trueccu",
      "clickstream": null,
      "closed_on": "2024-10-15T22:50:44.898Z",
      "custom_data": null,
      "created_on": "2024-10-15T22:30:54.569Z",
      "last_updated_on": "2024-10-15T22:50:44.899Z",
      "_instance": "ss01"
    },
    {
      "id": 6933,
      "cuid": "33r5lc0x3j17b96kjrue",
      "source": null,
      "successful_jobs": 1,
      "failed_jobs": 0,
      "total_jobs": 1,
      "agent_session_id": "7bd50b39-5a10-412c-89b2-c6ddba028105",
      "cardholder_id": null,
      "financial_institution_id": 166,
      "financial_institution_lookup_key": "centracu",
      "clickstream": [
        {
          "url": "/select-merchants",
          "timestamp": "2024-10-15T23:27:48.462Z",
          "page_title": "Select Merchants"
        },
        {
          "url": "/user-data-collection",
          "timestamp": "2024-10-15T23:27:59.693Z",
          "page_title": "User Data Collection"
        },
        {
          "url": "/user-data-collection",
          "timestamp": "2024-10-15T23:29:24.531Z",
          "page_title": "User Data Collection"
        },
        {
          "url": "/credential-entry",
          "timestamp": "2024-10-15T23:29:24.657Z",
          "page_title": "Credential Entry"
        }
      ],
      "closed_on": "2024-10-15T23:50:44.586Z",
      "custom_data": null,
      "created_on": "2024-10-15T23:29:24.140Z",
      "last_updated_on": "2024-10-15T23:50:44.587Z",
      "_instance": "ss01"
    },
    {
      "id": 25639,
      "cuid": "ojatfzxv3ow0krzqi6fv",
      "source": null,
      "successful_jobs": 0,
      "failed_jobs": 0,
      "total_jobs": 3,
      "agent_session_id": "0ec1b62e-9ac8-4fe8-8970-6a098c6d3131",
      "cardholder_id": null,
      "financial_institution_id": 200,
      "financial_institution_lookup_key": "mygecu",
      "clickstream": [
        {
          "url": "/select-merchants",
          "timestamp": "2024-10-15T01:14:17.644Z",
          "page_title": "Select Merchants"
        },
        {
          "url": "/user-data-collection",
          "timestamp": "2024-10-15T01:15:56.521Z",
          "page_title": "User Data Collection"
        },
        {
          "url": "/credential-entry",
          "timestamp": "2024-10-15T01:18:41.518Z",
          "page_title": "Credential Entry"
        },
        {
          "url": "/credential-entry",
          "timestamp": "2024-10-15T01:18:41.675Z",
          "page_title": "Credential Entry"
        },
        {
          "url": "/select-merchants",
          "timestamp": "2024-10-15T01:27:30.063Z",
          "page_title": "Select Merchants"
        },
        {
          "url": "/select-merchants",
          "timestamp": "2024-10-15T01:27:36.310Z",
          "page_title": "Select Merchants"
        },
        {
          "url": "/user-data-collection",
          "timestamp": "2024-10-15T01:27:36.353Z",
          "page_title": "User Data Collection"
        }
      ],
      "closed_on": "2024-10-15T01:44:34.038Z",
      "custom_data": {
        "digital_onboarding": {
          "team_id": "a7fda094-f57c-406b-892e-abb293bc75b9",
          "contact_id": "ea731efc-926e-488f-b2eb-89b1fd247951",
          "page_id": "93f5e87b-134b-41f0-a1ed-aeb215d1cdf4",
          "journey_id": "a3fde9de-0680-4d1f-ba5e-f9ccc90c3f82",
          "slug": "S1_MdwTba"
        }
      },
      "created_on": "2024-10-15T01:18:40.481Z",
      "last_updated_on": "2024-10-15T01:44:34.040Z",
      "_instance": "digital-onboarding"
    },
    {
      "id": 25640,
      "cuid": "p9d3ephlpytxx82etiy8",
      "source": null,
      "successful_jobs": 0,
      "failed_jobs": 0,
      "total_jobs": 0,
      "agent_session_id": "4d96572e-b781-413d-80b3-122573c26fc0",
      "cardholder_id": null,
      "financial_institution_id": 3,
      "financial_institution_lookup_key": "mybank",
      "clickstream": [
        {
          "url": "/select-merchants",
          "timestamp": "2024-10-15T13:13:37.745Z",
          "page_title": "Select Merchants"
        },
        {
          "url": "/user-data-collection",
          "timestamp": "2024-10-15T13:14:24.313Z",
          "page_title": "User Data Collection"
        },
        {
          "url": "/user-data-collection",
          "timestamp": "2024-10-15T13:14:54.233Z",
          "page_title": "User Data Collection"
        },
        {
          "url": "/credential-entry",
          "timestamp": "2024-10-15T13:14:54.373Z",
          "page_title": "Credential Entry"
        }
      ],
      "closed_on": "2024-10-15T13:34:34.278Z",
      "custom_data": {
        "digital_onboarding": {
          "team_id": "e4fb4ff4-8984-4d6f-b902-a9c2275bbf70",
          "contact_id": "400ea2bc-291f-499f-957c-ea757a839b9d",
          "page_id": "d9ccaa42-d618-49a8-8fbc-f02f96c31b71",
          "journey_id": "855e0ea6-ad45-43b8-9a6a-f486802c0264",
          "slug": "SyKMiYvOj"
        }
      },
      "created_on": "2024-10-15T13:14:53.727Z",
      "last_updated_on": "2024-10-15T13:34:34.280Z",
      "_instance": "digital-onboarding"
    },
    {
      "id": 25641,
      "cuid": "kzgx08cepizivutw2czq",
      "source": null,
      "successful_jobs": 1,
      "failed_jobs": 0,
      "total_jobs": 2,
      "agent_session_id": "2b7f657f-1b17-4c94-a437-4b76774fcd16",
      "cardholder_id": null,
      "financial_institution_id": 134,
      "financial_institution_lookup_key": "fhfcu",
      "clickstream": [
        {
          "url": "/select-merchants",
          "timestamp": "2024-10-15T20:27:19.881Z",
          "page_title": "Select Merchants"
        },
        {
          "url": "/user-data-collection",
          "timestamp": "2024-10-15T20:28:52.170Z",
          "page_title": "User Data Collection"
        },
        {
          "url": "/credential-entry",
          "timestamp": "2024-10-15T20:32:22.016Z",
          "page_title": "Credential Entry"
        }
      ],
      "closed_on": "2024-10-15T20:54:34.204Z",
      "custom_data": {
        "digital_onboarding": {
          "team_id": "c8137945-1110-4a95-b6c2-e11686ee9fc0",
          "contact_id": "d49226f6-d136-4f9d-a21d-1b7466fe4daa",
          "page_id": "ae64d422-64f6-4e8b-bbf8-fee80df67c4d",
          "journey_id": "86a579ae-4a0e-48a9-b795-ac42abc4da07",
          "slug": "BJAr4qA2j"
        }
      },
      "created_on": "2024-10-15T20:32:21.316Z",
      "last_updated_on": "2024-10-15T20:54:34.205Z",
      "_instance": "digital-onboarding"
    },
    {
      "id": 5683,
      "cuid": "7TJRRLLT9P7SX5JSWH_2181_294fe5e3-8d41-4223-8e9a-2da85e10d84c",
      "source": null,
      "successful_jobs": 0,
      "failed_jobs": 0,
      "total_jobs": 0,
      "agent_session_id": "25687530-017a-411e-81e2-5bf0c486efd1",
      "cardholder_id": null,
      "financial_institution_id": 3,
      "financial_institution_lookup_key": "msufcu",
      "clickstream": [
        {
          "url": "/select-merchants",
          "timestamp": "2024-10-15T00:22:31.446Z",
          "page_title": "Select Merchants"
        },
        {
          "url": "/select-merchants",
          "timestamp": "2024-10-15T00:22:31.543Z",
          "page_title": "Select Merchants"
        },
        {
          "url": "/select-merchants/missing_fields",
          "timestamp": "2024-10-15T00:22:45.863Z",
          "page_title": "Select Merchants"
        },
        {
          "url": "/select-merchants",
          "timestamp": "2024-10-15T00:22:58.992Z",
          "page_title": "Select Merchants"
        },
        {
          "url": "/user-data-collection",
          "timestamp": "2024-10-15T00:22:59.117Z",
          "page_title": "User Data Collection"
        },
        {
          "url": "/credential-entry",
          "timestamp": "2024-10-15T00:22:59.235Z",
          "page_title": "Credential Entry"
        }
      ],
      "closed_on": "2024-10-15T00:39:35.993Z",
      "custom_data": null,
      "created_on": "2024-10-15T00:22:31.243Z",
      "last_updated_on": "2024-10-15T00:39:35.994Z",
      "_instance": "msu"
    },
    {
      "id": 5684,
      "cuid": "PQBWM4V4BQRRLXC43W_133_d75204b9-b1d0-4cea-a1c3-271dc52653b4",
      "source": null,
      "successful_jobs": 0,
      "failed_jobs": 0,
      "total_jobs": 0,
      "agent_session_id": "41b729de-59b2-433c-abec-8937b15080d6",
      "cardholder_id": null,
      "financial_institution_id": 3,
      "financial_institution_lookup_key": "msufcu",
      "clickstream": [
        {
          "url": "/select-merchants",
          "timestamp": "2024-10-15T00:34:38.957Z",
          "page_title": "Select Merchants"
        },
        {
          "url": "/select-merchants",
          "timestamp": "2024-10-15T00:34:39.006Z",
          "page_title": "Select Merchants"
        }
      ],
      "closed_on": "2024-10-15T00:54:34.674Z",
      "custom_data": null,
      "created_on": "2024-10-15T00:34:38.805Z",
      "last_updated_on": "2024-10-15T00:54:34.834Z",
      "_instance": "msu"
    },
    {
      "id": 5685,
      "cuid": "81FM37718JM5NZMRTM_544_847114d9-3ffa-48e4-89d9-5fc5e2689731",
      "source": null,
      "successful_jobs": 0,
      "failed_jobs": 0,
      "total_jobs": 0,
      "agent_session_id": "24672ff6-7f56-4eb9-b647-d5705d0f8661",
      "cardholder_id": null,
      "financial_institution_id": 3,
      "financial_institution_lookup_key": "msufcu",
      "clickstream": [
        {
          "url": "/select-merchants",
          "timestamp": "2024-10-15T00:54:42.723Z",
          "page_title": "Select Merchants"
        },
        {
          "url": "/select-merchants",
          "timestamp": "2024-10-15T00:54:42.731Z",
          "page_title": "Select Merchants"
        }
      ],
      "closed_on": "2024-10-15T01:14:34.193Z",
      "custom_data": null,
      "created_on": "2024-10-15T00:54:42.623Z",
      "last_updated_on": "2024-10-15T01:14:34.194Z",
      "_instance": "msu"
    },
    {
      "id": 5686,
      "cuid": "3S3MJTSKJ2XKBQP9KX_377_51f88d97-37b2-46f5-89fa-0da9d1332c27",
      "source": null,
      "successful_jobs": 0,
      "failed_jobs": 0,
      "total_jobs": 0,
      "agent_session_id": "fc5281a1-72b2-48fa-b3b6-590837d4c8b4",
      "cardholder_id": null,
      "financial_institution_id": 3,
      "financial_institution_lookup_key": "msufcu",
      "clickstream": [
        {
          "url": "/select-merchants",
          "timestamp": "2024-10-15T01:50:59.982Z",
          "page_title": "Select Merchants"
        },
        {
          "url": "/select-merchants",
          "timestamp": "2024-10-15T01:51:00.411Z",
          "page_title": "Select Merchants"
        }
      ],
      "closed_on": "2024-10-15T02:09:34.261Z",
      "custom_data": null,
      "created_on": "2024-10-15T01:50:59.866Z",
      "last_updated_on": "2024-10-15T02:09:34.263Z",
      "_instance": "msu"
    },
    {
      "id": 5687,
      "cuid": "S617WXWZBYJ59XC4ST_259_d68834e4-9aa8-448b-8f16-ab8f25f80be3",
      "source": null,
      "successful_jobs": 0,
      "failed_jobs": 0,
      "total_jobs": 0,
      "agent_session_id": "36b2fa92-62e6-4dcb-9920-535e6257902f",
      "cardholder_id": null,
      "financial_institution_id": 3,
      "financial_institution_lookup_key": "msufcu",
      "clickstream": [
        {
          "url": "/select-merchants",
          "timestamp": "2024-10-15T02:41:34.327Z",
          "page_title": "Select Merchants"
        },
        {
          "url": "/select-merchants",
          "timestamp": "2024-10-15T02:41:34.408Z",
          "page_title": "Select Merchants"
        }
      ],
      "closed_on": "2024-10-15T02:59:34.357Z",
      "custom_data": null,
      "created_on": "2024-10-15T02:41:35.217Z",
      "last_updated_on": "2024-10-15T02:59:34.361Z",
      "_instance": "msu"
    },
    {
      "id": 5688,
      "cuid": "HMLN5L2LH67N7BBKHJ_756_fbeec8e8-587e-405a-a88d-ef63d301cb7c",
      "source": null,
      "successful_jobs": 0,
      "failed_jobs": 0,
      "total_jobs": 0,
      "agent_session_id": "76f53bdd-8573-472b-802c-85b3b2e3ccd3",
      "cardholder_id": null,
      "financial_institution_id": 3,
      "financial_institution_lookup_key": "msufcu",
      "clickstream": [
        {
          "url": "/select-merchants",
          "timestamp": "2024-10-15T03:00:37.910Z",
          "page_title": "Select Merchants"
        },
        {
          "url": "/select-merchants",
          "timestamp": "2024-10-15T03:00:37.978Z",
          "page_title": "Select Merchants"
        }
      ],
      "closed_on": "2024-10-15T03:19:34.478Z",
      "custom_data": null,
      "created_on": "2024-10-15T03:00:37.730Z",
      "last_updated_on": "2024-10-15T03:19:34.479Z",
      "_instance": "msu"
    },
    {
      "id": 5689,
      "cuid": "54C6MYF981FL83555G_503_b1af1490-9957-444d-a574-948d54423c52",
      "source": null,
      "successful_jobs": 0,
      "failed_jobs": 0,
      "total_jobs": 0,
      "agent_session_id": "abddbb6b-a277-4a8e-8412-eff58fe868f9",
      "cardholder_id": null,
      "financial_institution_id": 3,
      "financial_institution_lookup_key": "msufcu",
      "clickstream": [
        {
          "url": "/select-merchants",
          "timestamp": "2024-10-15T05:45:53.205Z",
          "page_title": "Select Merchants"
        }
      ],
      "closed_on": "2024-10-15T06:04:34.507Z",
      "custom_data": null,
      "created_on": "2024-10-15T05:45:56.724Z",
      "last_updated_on": "2024-10-15T06:04:34.509Z",
      "_instance": "msu"
    },
    {
      "id": 5690,
      "cuid": "C6FVXPFMV736TCBJMD_595_3f716a4b-c55d-476b-8177-ff9a1fcc651f",
      "source": null,
      "successful_jobs": 0,
      "failed_jobs": 0,
      "total_jobs": 0,
      "agent_session_id": "2334c4eb-a100-4d06-88ba-606db74ac504",
      "cardholder_id": null,
      "financial_institution_id": 3,
      "financial_institution_lookup_key": "msufcu",
      "clickstream": [
        {
          "url": "/select-merchants",
          "timestamp": "2024-10-15T07:34:10.264Z",
          "page_title": "Select Merchants"
        },
        {
          "url": "/select-merchants",
          "timestamp": "2024-10-15T07:34:10.333Z",
          "page_title": "Select Merchants"
        }
      ],
      "closed_on": "2024-10-15T07:49:34.485Z",
      "custom_data": null,
      "created_on": "2024-10-15T07:34:10.092Z",
      "last_updated_on": "2024-10-15T07:49:34.487Z",
      "_instance": "msu"
    },
    {
      "id": 5691,
      "cuid": "RNMN56DBJYWWTNVHZ7_694_3cb39468-41b5-4c93-b9ee-b645ffb798c9",
      "source": null,
      "successful_jobs": 0,
      "failed_jobs": 0,
      "total_jobs": 0,
      "agent_session_id": "969d6b70-c772-4575-a653-4a41d31d1d4e",
      "cardholder_id": null,
      "financial_institution_id": 3,
      "financial_institution_lookup_key": "msufcu",
      "clickstream": [
        {
          "url": "/select-merchants",
          "timestamp": "2024-10-15T09:26:04.340Z",
          "page_title": "Select Merchants"
        },
        {
          "url": "/select-merchants",
          "timestamp": "2024-10-15T09:26:04.409Z",
          "page_title": "Select Merchants"
        }
      ],
      "closed_on": "2024-10-15T09:44:34.394Z",
      "custom_data": null,
      "created_on": "2024-10-15T09:26:04.151Z",
      "last_updated_on": "2024-10-15T09:44:34.396Z",
      "_instance": "msu"
    },
    {
      "id": 5692,
      "cuid": "DRSGVTHZ78G656K7ZP_292_eb1ba991-582e-454e-b394-f3a212f9d117",
      "source": null,
      "successful_jobs": 0,
      "failed_jobs": 0,
      "total_jobs": 0,
      "agent_session_id": "c34e0ec1-3953-4c72-8307-a8228621eaf5",
      "cardholder_id": null,
      "financial_institution_id": 3,
      "financial_institution_lookup_key": "msufcu",
      "clickstream": [
        {
          "url": "/select-merchants",
          "timestamp": "2024-10-15T09:30:35.198Z",
          "page_title": "Select Merchants"
        },
        {
          "url": "/select-merchants",
          "timestamp": "2024-10-15T09:30:35.246Z",
          "page_title": "Select Merchants"
        },
        {
          "url": "/select-merchants/missing_fields",
          "timestamp": "2024-10-15T09:30:59.983Z",
          "page_title": "Select Merchants"
        }
      ],
      "closed_on": "2024-10-15T09:49:34.526Z",
      "custom_data": null,
      "created_on": "2024-10-15T09:30:35.032Z",
      "last_updated_on": "2024-10-15T09:49:34.527Z",
      "_instance": "msu"
    },
    {
      "id": 5693,
      "cuid": "DMBWJSHQSZBPCGVTTF_50_b2c95336-a5d7-4d73-a3f5-6779fc117286",
      "source": null,
      "successful_jobs": 0,
      "failed_jobs": 0,
      "total_jobs": 0,
      "agent_session_id": "f6675333-73be-4b68-b488-93b86dd029e7",
      "cardholder_id": null,
      "financial_institution_id": 3,
      "financial_institution_lookup_key": "msufcu",
      "clickstream": [
        {
          "url": "/select-merchants",
          "timestamp": "2024-10-15T10:57:23.214Z",
          "page_title": "Select Merchants"
        }
      ],
      "closed_on": "2024-10-15T11:14:34.549Z",
      "custom_data": null,
      "created_on": "2024-10-15T10:57:20.774Z",
      "last_updated_on": "2024-10-15T11:14:34.643Z",
      "_instance": "msu"
    },
    {
      "id": 5694,
      "cuid": "DMBWJSHQSZBPCGVTTF_50_f2f04afb-28e0-4bbe-acc6-1e223c263911",
      "source": null,
      "successful_jobs": 0,
      "failed_jobs": 0,
      "total_jobs": 0,
      "agent_session_id": "3513fe35-07de-44b2-959b-8b433b5aad62",
      "cardholder_id": null,
      "financial_institution_id": 3,
      "financial_institution_lookup_key": "msufcu",
      "clickstream": [
        {
          "url": "/select-merchants",
          "timestamp": "2024-10-15T10:57:23.389Z",
          "page_title": "Select Merchants"
        },
        {
          "url": "/select-merchants",
          "timestamp": "2024-10-15T10:57:23.396Z",
          "page_title": "Select Merchants"
        }
      ],
      "closed_on": "2024-10-15T11:14:34.778Z",
      "custom_data": null,
      "created_on": "2024-10-15T10:57:20.786Z",
      "last_updated_on": "2024-10-15T11:14:34.780Z",
      "_instance": "msu"
    },
    {
      "id": 5695,
      "cuid": "W38QBX7WDLB681LZ9X_419_efcae56e-7a92-43d7-bb37-d99855501382",
      "source": null,
      "successful_jobs": 0,
      "failed_jobs": 0,
      "total_jobs": 0,
      "agent_session_id": "4cfbbde4-d8c3-4f6d-9a05-8f2e770dcfbd",
      "cardholder_id": null,
      "financial_institution_id": 3,
      "financial_institution_lookup_key": "msufcu",
      "clickstream": [
        {
          "url": "/select-merchants",
          "timestamp": "2024-10-15T11:34:45.188Z",
          "page_title": "Select Merchants"
        },
        {
          "url": "/select-merchants",
          "timestamp": "2024-10-15T11:34:45.611Z",
          "page_title": "Select Merchants"
        },
        {
          "url": "/select-merchants/missing_fields",
          "timestamp": "2024-10-15T11:38:43.456Z",
          "page_title": "Select Merchants"
        }
      ],
      "closed_on": "2024-10-15T11:54:34.744Z",
      "custom_data": null,
      "created_on": "2024-10-15T11:34:45.283Z",
      "last_updated_on": "2024-10-15T11:54:34.840Z",
      "_instance": "msu"
    },
    {
      "id": 5696,
      "cuid": "5PSLHXTSWR6YFRNX9R_26_861b1555-c231-4695-9baa-f4de2a692b1b",
      "source": null,
      "successful_jobs": 0,
      "failed_jobs": 0,
      "total_jobs": 0,
      "agent_session_id": "98a14626-06de-4539-8368-0f17d46915d9",
      "cardholder_id": null,
      "financial_institution_id": 3,
      "financial_institution_lookup_key": "msufcu",
      "clickstream": [
        {
          "url": "/select-merchants",
          "timestamp": "2024-10-15T11:38:03.557Z",
          "page_title": "Select Merchants"
        }
      ],
      "closed_on": "2024-10-15T11:54:34.738Z",
      "custom_data": null,
      "created_on": "2024-10-15T11:38:03.393Z",
      "last_updated_on": "2024-10-15T11:54:34.743Z",
      "_instance": "msu"
    },
    {
      "id": 5697,
      "cuid": "P7ZX4ML626X5N47B9B_620_37aa92e9-fe4d-45f5-879e-686b319a74cd",
      "source": null,
      "successful_jobs": 2,
      "failed_jobs": 0,
      "total_jobs": 6,
      "agent_session_id": "1bd48605-9aa1-4a67-a208-db379f5bf8b3",
      "cardholder_id": null,
      "financial_institution_id": 3,
      "financial_institution_lookup_key": "msufcu",
      "clickstream": [
        {
          "url": "/select-merchants",
          "timestamp": "2024-10-15T12:27:38.943Z",
          "page_title": "Select Merchants"
        },
        {
          "url": "/select-merchants",
          "timestamp": "2024-10-15T12:27:38.990Z",
          "page_title": "Select Merchants"
        },
        {
          "url": "/select-merchants/missing_fields",
          "timestamp": "2024-10-15T12:28:47.754Z",
          "page_title": "Select Merchants"
        },
        {
          "url": "/select-merchants",
          "timestamp": "2024-10-15T12:29:00.595Z",
          "page_title": "Select Merchants"
        },
        {
          "url": "/user-data-collection",
          "timestamp": "2024-10-15T12:29:00.680Z",
          "page_title": "User Data Collection"
        },
        {
          "url": "/credential-entry",
          "timestamp": "2024-10-15T12:29:00.769Z",
          "page_title": "Credential Entry"
        }
      ],
      "closed_on": "2024-10-15T12:54:34.866Z",
      "custom_data": null,
      "created_on": "2024-10-15T12:27:38.791Z",
      "last_updated_on": "2024-10-15T12:54:34.868Z",
      "_instance": "msu"
    },
    {
      "id": 5698,
      "cuid": "B8B9G79J7Y9CSLRVX6_201_38858e8f-a73d-4991-8a33-a4a972f93edc",
      "source": null,
      "successful_jobs": 0,
      "failed_jobs": 0,
      "total_jobs": 0,
      "agent_session_id": "7fd8d85d-4df8-4032-b3a5-af5eca54dc1f",
      "cardholder_id": null,
      "financial_institution_id": 3,
      "financial_institution_lookup_key": "msufcu",
      "clickstream": [
        {
          "url": "/select-merchants",
          "timestamp": "2024-10-15T12:48:36.741Z",
          "page_title": "Select Merchants"
        }
      ],
      "closed_on": "2024-10-15T13:04:34.601Z",
      "custom_data": null,
      "created_on": "2024-10-15T12:48:36.497Z",
      "last_updated_on": "2024-10-15T13:04:34.602Z",
      "_instance": "msu"
    },
    {
      "id": 5699,
      "cuid": "3RG8CK8JLV243VFG7V_1018_32b73ae0-209f-4c13-bd64-8acdcb96797d",
      "source": null,
      "successful_jobs": 0,
      "failed_jobs": 0,
      "total_jobs": 0,
      "agent_session_id": "388d199e-cf65-4390-90d1-5f94e0f7c809",
      "cardholder_id": null,
      "financial_institution_id": 3,
      "financial_institution_lookup_key": "msufcu",
      "clickstream": [
        {
          "url": "/select-merchants",
          "timestamp": "2024-10-15T13:02:23.373Z",
          "page_title": "Select Merchants"
        },
        {
          "url": "/select-merchants",
          "timestamp": "2024-10-15T13:02:23.512Z",
          "page_title": "Select Merchants"
        },
        {
          "url": "/select-merchants",
          "timestamp": "2024-10-15T13:02:25.811Z",
          "page_title": "Select Merchants"
        }
      ],
      "closed_on": "2024-10-15T13:19:34.538Z",
      "custom_data": null,
      "created_on": "2024-10-15T13:02:23.209Z",
      "last_updated_on": "2024-10-15T13:19:34.541Z",
      "_instance": "msu"
    },
    {
      "id": 5700,
      "cuid": "VMVH9LP3BPX4RFGYDV_144_04cebf98-0901-445e-adfa-6aa99cf02a44",
      "source": null,
      "successful_jobs": 0,
      "failed_jobs": 0,
      "total_jobs": 0,
      "agent_session_id": "c5faad4c-778b-48c1-a72f-3a5885e5b8de",
      "cardholder_id": null,
      "financial_institution_id": 3,
      "financial_institution_lookup_key": "msufcu",
      "clickstream": [
        {
          "url": "/select-merchants",
          "timestamp": "2024-10-15T13:56:50.302Z",
          "page_title": "Select Merchants"
        },
        {
          "url": "/select-merchants",
          "timestamp": "2024-10-15T13:56:50.354Z",
          "page_title": "Select Merchants"
        }
      ],
      "closed_on": "2024-10-15T14:14:34.332Z",
      "custom_data": null,
      "created_on": "2024-10-15T13:56:50.085Z",
      "last_updated_on": "2024-10-15T14:14:34.334Z",
      "_instance": "msu"
    },
    {
      "id": 5701,
      "cuid": "ZNXS1FRSXPSBVXLWMT_49_e673f026-ae68-45f9-91e5-306ba3359649",
      "source": null,
      "successful_jobs": 0,
      "failed_jobs": 0,
      "total_jobs": 1,
      "agent_session_id": "d73e3220-9e32-42f3-918d-ebf35690e217",
      "cardholder_id": null,
      "financial_institution_id": 3,
      "financial_institution_lookup_key": "msufcu",
      "clickstream": [
        {
          "url": "/select-merchants",
          "timestamp": "2024-10-15T14:04:18.414Z",
          "page_title": "Select Merchants"
        },
        {
          "url": "/select-merchants",
          "timestamp": "2024-10-15T14:04:18.565Z",
          "page_title": "Select Merchants"
        },
        {
          "url": "/select-merchants/missing_fields",
          "timestamp": "2024-10-15T14:04:53.784Z",
          "page_title": "Select Merchants"
        },
        {
          "url": "/select-merchants",
          "timestamp": "2024-10-15T14:05:01.396Z",
          "page_title": "Select Merchants"
        },
        {
          "url": "/user-data-collection",
          "timestamp": "2024-10-15T14:05:01.574Z",
          "page_title": "User Data Collection"
        },
        {
          "url": "/credential-entry",
          "timestamp": "2024-10-15T14:05:01.736Z",
          "page_title": "Credential Entry"
        }
      ],
      "closed_on": "2024-10-15T14:24:34.473Z",
      "custom_data": null,
      "created_on": "2024-10-15T14:04:18.115Z",
      "last_updated_on": "2024-10-15T14:24:34.475Z",
      "_instance": "msu"
    },
    {
      "id": 5702,
      "cuid": "4M268SQXXHK7GDNR42_857_5dba0ded-0b25-48fd-99f4-6b9eab570aa1",
      "source": null,
      "successful_jobs": 0,
      "failed_jobs": 0,
      "total_jobs": 0,
      "agent_session_id": "e6a182e9-3258-461b-b265-1acd775a7bf5",
      "cardholder_id": null,
      "financial_institution_id": 3,
      "financial_institution_lookup_key": "msufcu",
      "clickstream": [
        {
          "url": "/select-merchants",
          "timestamp": "2024-10-15T15:09:33.125Z",
          "page_title": "Select Merchants"
        }
      ],
      "closed_on": "2024-10-15T15:29:34.480Z",
      "custom_data": null,
      "created_on": "2024-10-15T15:09:30.905Z",
      "last_updated_on": "2024-10-15T15:29:34.481Z",
      "_instance": "msu"
    },
    {
      "id": 5703,
      "cuid": "J759VJ33YLYYZPVMDS_609_fc13e7e3-8676-4d88-9ddf-91bcf201e357",
      "source": null,
      "successful_jobs": 0,
      "failed_jobs": 0,
      "total_jobs": 0,
      "agent_session_id": "0a55eac9-69be-4445-b03a-ed2bf87f598d",
      "cardholder_id": null,
      "financial_institution_id": 3,
      "financial_institution_lookup_key": "msufcu",
      "clickstream": [
        {
          "url": "/select-merchants",
          "timestamp": "2024-10-15T15:37:38.879Z",
          "page_title": "Select Merchants"
        },
        {
          "url": "/select-merchants",
          "timestamp": "2024-10-15T15:37:38.911Z",
          "page_title": "Select Merchants"
        },
        {
          "url": "/select-merchants/missing_fields",
          "timestamp": "2024-10-15T15:38:12.411Z",
          "page_title": "Select Merchants"
        },
        {
          "url": "/select-merchants",
          "timestamp": "2024-10-15T15:38:20.584Z",
          "page_title": "Select Merchants"
        },
        {
          "url": "/user-data-collection",
          "timestamp": "2024-10-15T15:38:20.716Z",
          "page_title": "User Data Collection"
        },
        {
          "url": "/credential-entry",
          "timestamp": "2024-10-15T15:38:20.967Z",
          "page_title": "Credential Entry"
        }
      ],
      "closed_on": "2024-10-15T15:54:34.460Z",
      "custom_data": null,
      "created_on": "2024-10-15T15:37:38.579Z",
      "last_updated_on": "2024-10-15T15:54:34.462Z",
      "_instance": "msu"
    },
    {
      "id": 5704,
      "cuid": "YKQQNQMRJ55LZMZ9GY_253_7e4eaa29-49be-460a-91bb-44eec7528914",
      "source": null,
      "successful_jobs": 0,
      "failed_jobs": 0,
      "total_jobs": 0,
      "agent_session_id": "ee7f9d88-0b51-4117-98cc-baa24aee0c44",
      "cardholder_id": null,
      "financial_institution_id": 3,
      "financial_institution_lookup_key": "msufcu",
      "clickstream": [
        {
          "url": "/select-merchants",
          "timestamp": "2024-10-15T15:41:56.130Z",
          "page_title": "Select Merchants"
        },
        {
          "url": "/select-merchants",
          "timestamp": "2024-10-15T15:41:56.211Z",
          "page_title": "Select Merchants"
        }
      ],
      "closed_on": "2024-10-15T15:59:34.496Z",
      "custom_data": null,
      "created_on": "2024-10-15T15:41:56.046Z",
      "last_updated_on": "2024-10-15T15:59:34.497Z",
      "_instance": "msu"
    },
    {
      "id": 5705,
      "cuid": "CXK711T436P6MNSQV3_1954_9cf1115c-2806-4f5d-9ad9-bf0e0f0f6f74",
      "source": null,
      "successful_jobs": 0,
      "failed_jobs": 0,
      "total_jobs": 0,
      "agent_session_id": "857379e6-0925-4d92-9d79-7c600a095ee3",
      "cardholder_id": null,
      "financial_institution_id": 3,
      "financial_institution_lookup_key": "msufcu",
      "clickstream": [
        {
          "url": "/select-merchants",
          "timestamp": "2024-10-15T16:09:28.547Z",
          "page_title": "Select Merchants"
        }
      ],
      "closed_on": "2024-10-15T16:24:35.449Z",
      "custom_data": null,
      "created_on": "2024-10-15T16:09:28.137Z",
      "last_updated_on": "2024-10-15T16:24:35.450Z",
      "_instance": "msu"
    },
    {
      "id": 5706,
      "cuid": "GJXHTZQB6WC748R3S9_1006_6dfbedf1-2830-410d-a117-ebd1abfca4c2",
      "source": null,
      "successful_jobs": 0,
      "failed_jobs": 0,
      "total_jobs": 1,
      "agent_session_id": "1e52f700-5df0-4732-863c-92636a7935bb",
      "cardholder_id": null,
      "financial_institution_id": 3,
      "financial_institution_lookup_key": "msufcu",
      "clickstream": [
        {
          "url": "/select-merchants",
          "timestamp": "2024-10-15T16:15:49.293Z",
          "page_title": "Select Merchants"
        },
        {
          "url": "/select-merchants",
          "timestamp": "2024-10-15T16:15:49.416Z",
          "page_title": "Select Merchants"
        },
        {
          "url": "/select-merchants/missing_fields",
          "timestamp": "2024-10-15T16:17:11.666Z",
          "page_title": "Select Merchants"
        },
        {
          "url": "/select-merchants",
          "timestamp": "2024-10-15T16:17:27.413Z",
          "page_title": "Select Merchants"
        },
        {
          "url": "/user-data-collection",
          "timestamp": "2024-10-15T16:17:27.546Z",
          "page_title": "User Data Collection"
        },
        {
          "url": "/credential-entry",
          "timestamp": "2024-10-15T16:17:27.640Z",
          "page_title": "Credential Entry"
        }
      ],
      "closed_on": "2024-10-15T16:34:34.382Z",
      "custom_data": null,
      "created_on": "2024-10-15T16:15:49.143Z",
      "last_updated_on": "2024-10-15T16:34:34.383Z",
      "_instance": "msu"
    },
    {
      "id": 5707,
      "cuid": "ZWCQZZJGL5Y2DXSM8D_1413_00838cbc-9893-4b65-b1fe-4691becf8d53",
      "source": null,
      "successful_jobs": 1,
      "failed_jobs": 0,
      "total_jobs": 4,
      "agent_session_id": "c36bd32e-a3ae-4311-ac0c-e05c3a5d96c4",
      "cardholder_id": null,
      "financial_institution_id": 3,
      "financial_institution_lookup_key": "msufcu",
      "clickstream": [
        {
          "url": "/select-merchants",
          "timestamp": "2024-10-15T16:57:12.303Z",
          "page_title": "Select Merchants"
        },
        {
          "url": "/select-merchants",
          "timestamp": "2024-10-15T16:57:12.352Z",
          "page_title": "Select Merchants"
        },
        {
          "url": "/select-merchants/missing_fields",
          "timestamp": "2024-10-15T16:57:53.784Z",
          "page_title": "Select Merchants"
        },
        {
          "url": "/select-merchants",
          "timestamp": "2024-10-15T16:58:10.810Z",
          "page_title": "Select Merchants"
        },
        {
          "url": "/user-data-collection",
          "timestamp": "2024-10-15T16:58:10.938Z",
          "page_title": "User Data Collection"
        },
        {
          "url": "/credential-entry",
          "timestamp": "2024-10-15T16:58:11.046Z",
          "page_title": "Credential Entry"
        }
      ],
      "closed_on": "2024-10-15T17:19:35.588Z",
      "custom_data": null,
      "created_on": "2024-10-15T16:57:12.089Z",
      "last_updated_on": "2024-10-15T17:19:35.589Z",
      "_instance": "msu"
    },
    {
      "id": 5708,
      "cuid": "J765YSNLBYHF32STRH_29_f0bf0562-4287-46a7-893f-cb36c3a6f984",
      "source": null,
      "successful_jobs": 0,
      "failed_jobs": 0,
      "total_jobs": 0,
      "agent_session_id": "51a404ad-24e8-4504-bb27-10e57603d044",
      "cardholder_id": null,
      "financial_institution_id": 3,
      "financial_institution_lookup_key": "msufcu",
      "clickstream": [
        {
          "url": "/select-merchants",
          "timestamp": "2024-10-15T16:57:22.119Z",
          "page_title": "Select Merchants"
        },
        {
          "url": "/select-merchants",
          "timestamp": "2024-10-15T16:57:22.195Z",
          "page_title": "Select Merchants"
        }
      ],
      "closed_on": "2024-10-15T17:14:35.251Z",
      "custom_data": null,
      "created_on": "2024-10-15T16:57:21.922Z",
      "last_updated_on": "2024-10-15T17:14:35.253Z",
      "_instance": "msu"
    },
    {
      "id": 5709,
      "cuid": "PL5V1TSHK389MM3439_372_827bd433-9f93-4293-9216-20d28a2a2229",
      "source": null,
      "successful_jobs": 0,
      "failed_jobs": 0,
      "total_jobs": 0,
      "agent_session_id": "b2516021-f884-469e-8561-f04914005643",
      "cardholder_id": null,
      "financial_institution_id": 3,
      "financial_institution_lookup_key": "msufcu",
      "clickstream": [
        {
          "url": "/select-merchants",
          "timestamp": "2024-10-15T17:00:39.030Z",
          "page_title": "Select Merchants"
        }
      ],
      "closed_on": "2024-10-15T17:19:35.482Z",
      "custom_data": null,
      "created_on": "2024-10-15T17:00:38.745Z",
      "last_updated_on": "2024-10-15T17:19:35.483Z",
      "_instance": "msu"
    },
    {
      "id": 5710,
      "cuid": "ZWCQZZJGL5Y2DXSM8D_1413_07113b0e-8655-405d-a3b2-42377eaf7b8d",
      "source": null,
      "successful_jobs": 0,
      "failed_jobs": 0,
      "total_jobs": 0,
      "agent_session_id": "c111a865-89d3-456b-a6d1-25a45ee6fb10",
      "cardholder_id": null,
      "financial_institution_id": 3,
      "financial_institution_lookup_key": "msufcu",
      "clickstream": [
        {
          "url": "/select-merchants",
          "timestamp": "2024-10-15T17:03:19.857Z",
          "page_title": "Select Merchants"
        },
        {
          "url": "/select-merchants",
          "timestamp": "2024-10-15T17:03:19.936Z",
          "page_title": "Select Merchants"
        }
      ],
      "closed_on": "2024-10-15T17:19:35.081Z",
      "custom_data": null,
      "created_on": "2024-10-15T17:03:19.675Z",
      "last_updated_on": "2024-10-15T17:19:35.179Z",
      "_instance": "msu"
    },
    {
      "id": 5711,
      "cuid": "VK8LCW6YKX1L1B3HMC_117_e0276765-5c2c-4dca-ba13-bfb8ad10f7e2",
      "source": null,
      "successful_jobs": 0,
      "failed_jobs": 0,
      "total_jobs": 0,
      "agent_session_id": "78a832c2-a215-41ff-a7cc-b8608a6717cd",
      "cardholder_id": null,
      "financial_institution_id": 3,
      "financial_institution_lookup_key": "msufcu",
      "clickstream": [
        {
          "url": "/select-merchants",
          "timestamp": "2024-10-15T17:11:47.107Z",
          "page_title": "Select Merchants"
        },
        {
          "url": "/select-merchants",
          "timestamp": "2024-10-15T17:11:47.156Z",
          "page_title": "Select Merchants"
        },
        {
          "url": "/select-merchants/missing_fields",
          "timestamp": "2024-10-15T17:12:25.402Z",
          "page_title": "Select Merchants"
        },
        {
          "url": "/select-merchants",
          "timestamp": "2024-10-15T17:12:35.905Z",
          "page_title": "Select Merchants"
        },
        {
          "url": "/user-data-collection",
          "timestamp": "2024-10-15T17:12:36.579Z",
          "page_title": "User Data Collection"
        },
        {
          "url": "/credential-entry",
          "timestamp": "2024-10-15T17:12:36.851Z",
          "page_title": "Credential Entry"
        }
      ],
      "closed_on": "2024-10-15T17:29:35.022Z",
      "custom_data": null,
      "created_on": "2024-10-15T17:11:47.248Z",
      "last_updated_on": "2024-10-15T17:29:35.024Z",
      "_instance": "msu"
    },
    {
      "id": 5712,
      "cuid": "CB9BCQ9JVHXHYPMRPL_804_7bdc5824-df95-4c96-86aa-b58852cc550e",
      "source": null,
      "successful_jobs": 0,
      "failed_jobs": 0,
      "total_jobs": 0,
      "agent_session_id": "c8c7dd3b-c99e-49fb-b78e-ef8a46555322",
      "cardholder_id": null,
      "financial_institution_id": 3,
      "financial_institution_lookup_key": "msufcu",
      "clickstream": [
        {
          "url": "/select-merchants",
          "timestamp": "2024-10-15T17:20:43.223Z",
          "page_title": "Select Merchants"
        },
        {
          "url": "/select-merchants",
          "timestamp": "2024-10-15T17:20:43.310Z",
          "page_title": "Select Merchants"
        }
      ],
      "closed_on": "2024-10-15T17:39:34.739Z",
      "custom_data": null,
      "created_on": "2024-10-15T17:20:42.953Z",
      "last_updated_on": "2024-10-15T17:39:34.740Z",
      "_instance": "msu"
    },
    {
      "id": 5713,
      "cuid": "SBCVG7DM5PR96TFPNS_115_ec8527ef-75ff-4535-8353-14985c582d0b",
      "source": null,
      "successful_jobs": 0,
      "failed_jobs": 0,
      "total_jobs": 0,
      "agent_session_id": "bde3b4c6-5a2d-453e-9bf4-1d75f42c9005",
      "cardholder_id": null,
      "financial_institution_id": 3,
      "financial_institution_lookup_key": "msufcu",
      "clickstream": [
        {
          "url": "/select-merchants",
          "timestamp": "2024-10-15T19:21:38.871Z",
          "page_title": "Select Merchants"
        },
        {
          "url": "/select-merchants",
          "timestamp": "2024-10-15T19:21:38.876Z",
          "page_title": "Select Merchants"
        },
        {
          "url": "/select-merchants/missing_fields",
          "timestamp": "2024-10-15T19:21:59.379Z",
          "page_title": "Select Merchants"
        },
        {
          "url": "/select-merchants",
          "timestamp": "2024-10-15T19:22:05.821Z",
          "page_title": "Select Merchants"
        },
        {
          "url": "/user-data-collection",
          "timestamp": "2024-10-15T19:22:05.923Z",
          "page_title": "User Data Collection"
        },
        {
          "url": "/credential-entry",
          "timestamp": "2024-10-15T19:22:06.018Z",
          "page_title": "Credential Entry"
        }
      ],
      "closed_on": "2024-10-15T19:39:34.225Z",
      "custom_data": null,
      "created_on": "2024-10-15T19:21:38.584Z",
      "last_updated_on": "2024-10-15T19:39:34.229Z",
      "_instance": "msu"
    },
    {
      "id": 5714,
      "cuid": "Z4RPFVM6T318XT6CSF_451_73ef755f-2cd0-45f4-a135-c7e4d5d38b31",
      "source": null,
      "successful_jobs": 0,
      "failed_jobs": 0,
      "total_jobs": 0,
      "agent_session_id": "2aba2513-af42-47db-afa0-ff63ebf2666a",
      "cardholder_id": null,
      "financial_institution_id": 3,
      "financial_institution_lookup_key": "msufcu",
      "clickstream": [
        {
          "url": "/select-merchants",
          "timestamp": "2024-10-15T19:55:42.333Z",
          "page_title": "Select Merchants"
        },
        {
          "url": "/select-merchants",
          "timestamp": "2024-10-15T19:55:42.429Z",
          "page_title": "Select Merchants"
        }
      ],
      "closed_on": "2024-10-15T20:14:35.198Z",
      "custom_data": null,
      "created_on": "2024-10-15T19:55:43.095Z",
      "last_updated_on": "2024-10-15T20:14:35.199Z",
      "_instance": "msu"
    },
    {
      "id": 5715,
      "cuid": "XR9VRR7TYQN1YWW8QM_1150_b5ee4770-c6b4-4c72-84af-14ba85dbf71f",
      "source": null,
      "successful_jobs": 0,
      "failed_jobs": 0,
      "total_jobs": 0,
      "agent_session_id": "6e9ef63b-2eff-447e-ba45-347ced23c044",
      "cardholder_id": null,
      "financial_institution_id": 3,
      "financial_institution_lookup_key": "msufcu",
      "clickstream": [
        {
          "url": "/select-merchants",
          "timestamp": "2024-10-15T20:07:16.908Z",
          "page_title": "Select Merchants"
        },
        {
          "url": "/select-merchants",
          "timestamp": "2024-10-15T20:07:16.974Z",
          "page_title": "Select Merchants"
        },
        {
          "url": "/select-merchants/missing_fields",
          "timestamp": "2024-10-15T20:08:16.889Z",
          "page_title": "Select Merchants"
        },
        {
          "url": "/select-merchants",
          "timestamp": "2024-10-15T20:08:25.795Z",
          "page_title": "Select Merchants"
        },
        {
          "url": "/user-data-collection",
          "timestamp": "2024-10-15T20:08:25.896Z",
          "page_title": "User Data Collection"
        },
        {
          "url": "/credential-entry",
          "timestamp": "2024-10-15T20:08:25.987Z",
          "page_title": "Credential Entry"
        }
      ],
      "closed_on": "2024-10-15T20:24:34.463Z",
      "custom_data": null,
      "created_on": "2024-10-15T20:07:16.572Z",
      "last_updated_on": "2024-10-15T20:24:34.465Z",
      "_instance": "msu"
    },
    {
      "id": 5716,
      "cuid": "HKNYCQPZWGXGTJP1CH_100_e4ca6b76-1d61-4d60-a34f-ed56d3d7a2ff",
      "source": null,
      "successful_jobs": 0,
      "failed_jobs": 0,
      "total_jobs": 0,
      "agent_session_id": "2c7746df-7ad1-4d17-95e2-0e171523e0a9",
      "cardholder_id": null,
      "financial_institution_id": 3,
      "financial_institution_lookup_key": "msufcu",
      "clickstream": [
        {
          "url": "/select-merchants",
          "timestamp": "2024-10-15T20:07:24.933Z",
          "page_title": "Select Merchants"
        },
        {
          "url": "/select-merchants",
          "timestamp": "2024-10-15T20:07:24.937Z",
          "page_title": "Select Merchants"
        }
      ],
      "closed_on": "2024-10-15T20:24:34.522Z",
      "custom_data": null,
      "created_on": "2024-10-15T20:07:24.645Z",
      "last_updated_on": "2024-10-15T20:24:34.524Z",
      "_instance": "msu"
    },
    {
      "id": 5717,
      "cuid": "VRGGP5STDHVPPFFL2G_793_a48d9053-419b-4da0-81c7-caf8711f2df4",
      "source": null,
      "successful_jobs": 0,
      "failed_jobs": 0,
      "total_jobs": 1,
      "agent_session_id": "feb767fc-406a-497f-a95c-0d2d97c69c3c",
      "cardholder_id": null,
      "financial_institution_id": 3,
      "financial_institution_lookup_key": "msufcu",
      "clickstream": [
        {
          "url": "/select-merchants",
          "timestamp": "2024-10-15T20:24:18.352Z",
          "page_title": "Select Merchants"
        },
        {
          "url": "/select-merchants",
          "timestamp": "2024-10-15T20:24:18.437Z",
          "page_title": "Select Merchants"
        },
        {
          "url": "/select-merchants/missing_fields",
          "timestamp": "2024-10-15T20:25:06.038Z",
          "page_title": "Select Merchants"
        },
        {
          "url": "/select-merchants",
          "timestamp": "2024-10-15T20:25:16.210Z",
          "page_title": "Select Merchants"
        },
        {
          "url": "/user-data-collection",
          "timestamp": "2024-10-15T20:25:16.324Z",
          "page_title": "User Data Collection"
        }
      ],
      "closed_on": "2024-10-15T20:44:34.462Z",
      "custom_data": null,
      "created_on": "2024-10-15T20:24:18.151Z",
      "last_updated_on": "2024-10-15T20:44:34.467Z",
      "_instance": "msu"
    },
    {
      "id": 5718,
      "cuid": "GJJY6TYJSYTKK7J6C3_239_4825dfaa-2a3a-4bd1-bf1d-f1b87d8251fd",
      "source": null,
      "successful_jobs": 0,
      "failed_jobs": 0,
      "total_jobs": 0,
      "agent_session_id": "525fc81f-1806-4f63-a659-b6428f907abe",
      "cardholder_id": null,
      "financial_institution_id": 3,
      "financial_institution_lookup_key": "msufcu",
      "clickstream": [
        {
          "url": "/select-merchants",
          "timestamp": "2024-10-15T20:53:02.747Z",
          "page_title": "Select Merchants"
        },
        {
          "url": "/select-merchants",
          "timestamp": "2024-10-15T20:53:02.830Z",
          "page_title": "Select Merchants"
        }
      ],
      "closed_on": "2024-10-15T21:09:35.493Z",
      "custom_data": null,
      "created_on": "2024-10-15T20:53:02.255Z",
      "last_updated_on": "2024-10-15T21:09:35.495Z",
      "_instance": "msu"
    },
    {
      "id": 5719,
      "cuid": "ZX31BN2HCY9M9S1C92_104_05d94b7b-f791-447b-9509-8bb17c2b06a5",
      "source": null,
      "successful_jobs": 0,
      "failed_jobs": 0,
      "total_jobs": 0,
      "agent_session_id": "2451802c-c504-4767-9f7c-fd55ecb5b593",
      "cardholder_id": null,
      "financial_institution_id": 3,
      "financial_institution_lookup_key": "msufcu",
      "clickstream": [
        {
          "url": "/select-merchants",
          "timestamp": "2024-10-15T21:01:39.946Z",
          "page_title": "Select Merchants"
        }
      ],
      "closed_on": "2024-10-15T21:19:35.102Z",
      "custom_data": null,
      "created_on": "2024-10-15T21:01:39.809Z",
      "last_updated_on": "2024-10-15T21:19:35.104Z",
      "_instance": "msu"
    },
    {
      "id": 5720,
      "cuid": "YZBDFHHB94ZN289QFK_681_4a6ffbf7-9183-4722-8047-7a7ceff8a637",
      "source": null,
      "successful_jobs": 1,
      "failed_jobs": 0,
      "total_jobs": 4,
      "agent_session_id": "3f38a5d3-3d17-4905-8dbf-49e0e430f38b",
      "cardholder_id": null,
      "financial_institution_id": 3,
      "financial_institution_lookup_key": "msufcu",
      "clickstream": [
        {
          "url": "/select-merchants",
          "timestamp": "2024-10-15T21:02:00.458Z",
          "page_title": "Select Merchants"
        },
        {
          "url": "/select-merchants",
          "timestamp": "2024-10-15T21:02:00.534Z",
          "page_title": "Select Merchants"
        },
        {
          "url": "/select-merchants/missing_fields",
          "timestamp": "2024-10-15T21:03:09.346Z",
          "page_title": "Select Merchants"
        },
        {
          "url": "/select-merchants",
          "timestamp": "2024-10-15T21:03:25.015Z",
          "page_title": "Select Merchants"
        },
        {
          "url": "/user-data-collection",
          "timestamp": "2024-10-15T21:03:25.114Z",
          "page_title": "User Data Collection"
        },
        {
          "url": "/credential-entry",
          "timestamp": "2024-10-15T21:03:25.222Z",
          "page_title": "Credential Entry"
        }
      ],
      "closed_on": "2024-10-15T21:24:34.908Z",
      "custom_data": null,
      "created_on": "2024-10-15T21:02:00.262Z",
      "last_updated_on": "2024-10-15T21:24:34.909Z",
      "_instance": "msu"
    },
    {
      "id": 5721,
      "cuid": "43DZ3MX7WPXCBFW827_2004_d614c20f-2afd-4ca7-b141-d0d01b08a512",
      "source": null,
      "successful_jobs": 0,
      "failed_jobs": 0,
      "total_jobs": 0,
      "agent_session_id": "3b525d8d-d518-46a2-9c1a-5f15f21f4026",
      "cardholder_id": null,
      "financial_institution_id": 3,
      "financial_institution_lookup_key": "msufcu",
      "clickstream": [
        {
          "url": "/select-merchants",
          "timestamp": "2024-10-15T21:06:31.304Z",
          "page_title": "Select Merchants"
        }
      ],
      "closed_on": "2024-10-15T21:24:34.981Z",
      "custom_data": null,
      "created_on": "2024-10-15T21:06:31.901Z",
      "last_updated_on": "2024-10-15T21:24:34.986Z",
      "_instance": "msu"
    },
    {
      "id": 5722,
      "cuid": "SB24SC3ZRX1DR96FLC_1782_5d905b06-85e0-4ce4-8d8a-831b996215fa",
      "source": null,
      "successful_jobs": 0,
      "failed_jobs": 0,
      "total_jobs": 1,
      "agent_session_id": "93f608f1-cd6e-44c8-b5fa-1b52bee8b135",
      "cardholder_id": null,
      "financial_institution_id": 3,
      "financial_institution_lookup_key": "msufcu",
      "clickstream": [
        {
          "url": "/select-merchants",
          "timestamp": "2024-10-15T21:07:26.112Z",
          "page_title": "Select Merchants"
        },
        {
          "url": "/select-merchants",
          "timestamp": "2024-10-15T21:07:26.174Z",
          "page_title": "Select Merchants"
        },
        {
          "url": "/select-merchants/missing_fields",
          "timestamp": "2024-10-15T21:07:43.285Z",
          "page_title": "Select Merchants"
        },
        {
          "url": "/select-merchants",
          "timestamp": "2024-10-15T21:08:05.223Z",
          "page_title": "Select Merchants"
        },
        {
          "url": "/user-data-collection",
          "timestamp": "2024-10-15T21:08:05.321Z",
          "page_title": "User Data Collection"
        },
        {
          "url": "/credential-entry",
          "timestamp": "2024-10-15T21:08:05.429Z",
          "page_title": "Credential Entry"
        },
        {
          "url": "/select-merchants",
          "timestamp": "2024-10-15T21:09:43.619Z",
          "page_title": "Select Merchants"
        }
      ],
      "closed_on": "2024-10-15T21:29:34.937Z",
      "custom_data": null,
      "created_on": "2024-10-15T21:07:25.867Z",
      "last_updated_on": "2024-10-15T21:29:35.031Z",
      "_instance": "msu"
    },
    {
      "id": 5723,
      "cuid": "YZBDFHHB94ZN289QFK_681_0c50a27f-0ca3-4842-9e5a-3bcbcb317d87",
      "source": null,
      "successful_jobs": 0,
      "failed_jobs": 0,
      "total_jobs": 0,
      "agent_session_id": "061f5e54-7d2c-4e9b-9dda-ac3e702f50a7",
      "cardholder_id": null,
      "financial_institution_id": 3,
      "financial_institution_lookup_key": "msufcu",
      "clickstream": [
        {
          "url": "/select-merchants",
          "timestamp": "2024-10-15T21:07:49.401Z",
          "page_title": "Select Merchants"
        },
        {
          "url": "/select-merchants",
          "timestamp": "2024-10-15T21:07:49.832Z",
          "page_title": "Select Merchants"
        }
      ],
      "closed_on": "2024-10-15T21:24:34.371Z",
      "custom_data": null,
      "created_on": "2024-10-15T21:07:49.225Z",
      "last_updated_on": "2024-10-15T21:24:34.397Z",
      "_instance": "msu"
    },
    {
      "id": 5724,
      "cuid": "1F3Z7PYBKMZJMDRCD3_819_0e3dda68-7560-4dd0-9177-87d72f6badf2",
      "source": null,
      "successful_jobs": 0,
      "failed_jobs": 0,
      "total_jobs": 0,
      "agent_session_id": "ece21bb6-ff98-4be8-a406-ddd05c5d6cbb",
      "cardholder_id": null,
      "financial_institution_id": 3,
      "financial_institution_lookup_key": "msufcu",
      "clickstream": [
        {
          "url": "/select-merchants",
          "timestamp": "2024-10-15T21:14:41.506Z",
          "page_title": "Select Merchants"
        },
        {
          "url": "/select-merchants",
          "timestamp": "2024-10-15T21:14:41.590Z",
          "page_title": "Select Merchants"
        }
      ],
      "closed_on": "2024-10-15T21:34:34.632Z",
      "custom_data": null,
      "created_on": "2024-10-15T21:14:41.270Z",
      "last_updated_on": "2024-10-15T21:34:34.633Z",
      "_instance": "msu"
    },
    {
      "id": 5725,
      "cuid": "4RKCF9HHJR3XMSWGY4_508_02ab718b-00a6-4047-98bd-c99dd55953f7",
      "source": null,
      "successful_jobs": 0,
      "failed_jobs": 0,
      "total_jobs": 0,
      "agent_session_id": "7d1fea52-c9e7-4b84-bb18-b7d052e77be7",
      "cardholder_id": null,
      "financial_institution_id": 3,
      "financial_institution_lookup_key": "msufcu",
      "clickstream": [
        {
          "url": "/select-merchants",
          "timestamp": "2024-10-15T21:23:39.252Z",
          "page_title": "Select Merchants"
        }
      ],
      "closed_on": "2024-10-15T21:39:34.790Z",
      "custom_data": null,
      "created_on": "2024-10-15T21:23:38.701Z",
      "last_updated_on": "2024-10-15T21:39:34.791Z",
      "_instance": "msu"
    },
    {
      "id": 5726,
      "cuid": "X78Z41YJP59WQKXR6Q_24_311019ea-0a0b-4112-ad08-5533c56b88f9",
      "source": null,
      "successful_jobs": 0,
      "failed_jobs": 0,
      "total_jobs": 0,
      "agent_session_id": "7ad70edd-3b07-4288-abee-313e32279ee8",
      "cardholder_id": null,
      "financial_institution_id": 3,
      "financial_institution_lookup_key": "msufcu",
      "clickstream": [
        {
          "url": "/select-merchants",
          "timestamp": "2024-10-15T21:36:30.863Z",
          "page_title": "Select Merchants"
        },
        {
          "url": "/select-merchants",
          "timestamp": "2024-10-15T21:36:30.934Z",
          "page_title": "Select Merchants"
        }
      ],
      "closed_on": "2024-10-15T21:54:34.368Z",
      "custom_data": null,
      "created_on": "2024-10-15T21:36:30.693Z",
      "last_updated_on": "2024-10-15T21:54:34.369Z",
      "_instance": "msu"
    },
    {
      "id": 5727,
      "cuid": "RLZWWL2F24W74XR48F_1832_327e5e36-763f-43a8-a912-632f9defab5d",
      "source": null,
      "successful_jobs": 0,
      "failed_jobs": 0,
      "total_jobs": 1,
      "agent_session_id": "f56402e7-9b13-4084-9589-a930c74f8778",
      "cardholder_id": null,
      "financial_institution_id": 3,
      "financial_institution_lookup_key": "msufcu",
      "clickstream": [
        {
          "url": "/select-merchants",
          "timestamp": "2024-10-15T22:32:27.837Z",
          "page_title": "Select Merchants"
        },
        {
          "url": "/select-merchants",
          "timestamp": "2024-10-15T22:32:27.883Z",
          "page_title": "Select Merchants"
        },
        {
          "url": "/select-merchants/missing_fields",
          "timestamp": "2024-10-15T22:33:23.340Z",
          "page_title": "Select Merchants"
        },
        {
          "url": "/select-merchants",
          "timestamp": "2024-10-15T22:33:36.259Z",
          "page_title": "Select Merchants"
        },
        {
          "url": "/user-data-collection",
          "timestamp": "2024-10-15T22:33:36.396Z",
          "page_title": "User Data Collection"
        },
        {
          "url": "/credential-entry",
          "timestamp": "2024-10-15T22:33:36.541Z",
          "page_title": "Credential Entry"
        }
      ],
      "closed_on": "2024-10-15T22:54:34.965Z",
      "custom_data": null,
      "created_on": "2024-10-15T22:32:27.623Z",
      "last_updated_on": "2024-10-15T22:54:34.966Z",
      "_instance": "msu"
    },
    {
      "id": 5728,
      "cuid": "DDMTTYQDGVDS1KMFRY_376_9a498f8d-f9ba-4bd7-a547-925f37417798",
      "source": null,
      "successful_jobs": 0,
      "failed_jobs": 0,
      "total_jobs": 0,
      "agent_session_id": "d0f4fec9-cd6d-477e-930f-ac08480951d6",
      "cardholder_id": null,
      "financial_institution_id": 3,
      "financial_institution_lookup_key": "msufcu",
      "clickstream": [
        {
          "url": "/select-merchants",
          "timestamp": "2024-10-15T22:50:54.538Z",
          "page_title": "Select Merchants"
        },
        {
          "url": "/select-merchants",
          "timestamp": "2024-10-15T22:50:54.620Z",
          "page_title": "Select Merchants"
        }
      ],
      "closed_on": "2024-10-15T23:09:34.864Z",
      "custom_data": null,
      "created_on": "2024-10-15T22:50:54.356Z",
      "last_updated_on": "2024-10-15T23:09:34.865Z",
      "_instance": "msu"
    },
    {
      "id": 5729,
      "cuid": "GKK4DJP8KY2GF1P3NS_306_9a37463e-f4a1-478c-a026-eec35ea6270d",
      "source": null,
      "successful_jobs": 0,
      "failed_jobs": 0,
      "total_jobs": 0,
      "agent_session_id": "e2c63529-ec6b-4e91-9e3f-76ee10da2c49",
      "cardholder_id": null,
      "financial_institution_id": 3,
      "financial_institution_lookup_key": "msufcu",
      "clickstream": [
        {
          "url": "/select-merchants",
          "timestamp": "2024-10-15T22:55:06.529Z",
          "page_title": "Select Merchants"
        },
        {
          "url": "/select-merchants",
          "timestamp": "2024-10-15T22:55:06.594Z",
          "page_title": "Select Merchants"
        }
      ],
      "closed_on": "2024-10-15T23:14:34.660Z",
      "custom_data": null,
      "created_on": "2024-10-15T22:55:06.329Z",
      "last_updated_on": "2024-10-15T23:14:34.755Z",
      "_instance": "msu"
    },
    {
      "id": 5730,
      "cuid": "VDHG9DXLXCYD2JHVWP_253_49b60a7e-8684-46ea-9aaf-fadd3aa1fe86",
      "source": null,
      "successful_jobs": 0,
      "failed_jobs": 0,
      "total_jobs": 0,
      "agent_session_id": "fbbe1667-3676-4451-9251-f06d47bedd80",
      "cardholder_id": null,
      "financial_institution_id": 3,
      "financial_institution_lookup_key": "msufcu",
      "clickstream": [
        {
          "url": "/select-merchants",
          "timestamp": "2024-10-15T23:03:10.482Z",
          "page_title": "Select Merchants"
        },
        {
          "url": "/select-merchants",
          "timestamp": "2024-10-15T23:03:10.544Z",
          "page_title": "Select Merchants"
        },
        {
          "url": "/select-merchants/missing_fields",
          "timestamp": "2024-10-15T23:03:26.900Z",
          "page_title": "Select Merchants"
        },
        {
          "url": "/select-merchants",
          "timestamp": "2024-10-15T23:03:37.781Z",
          "page_title": "Select Merchants"
        },
        {
          "url": "/user-data-collection",
          "timestamp": "2024-10-15T23:03:37.923Z",
          "page_title": "User Data Collection"
        },
        {
          "url": "/credential-entry",
          "timestamp": "2024-10-15T23:03:38.032Z",
          "page_title": "Credential Entry"
        }
      ],
      "closed_on": "2024-10-15T23:19:34.905Z",
      "custom_data": null,
      "created_on": "2024-10-15T23:03:10.361Z",
      "last_updated_on": "2024-10-15T23:19:34.907Z",
      "_instance": "msu"
    },
    {
      "id": 5731,
      "cuid": "ZTKVGSB15FMWM3XC2S_246_3992dead-ae33-4d78-82ed-38e063b50f14",
      "source": null,
      "successful_jobs": 0,
      "failed_jobs": 0,
      "total_jobs": 0,
      "agent_session_id": "36c1c8ca-2e1f-4648-bc3c-665d386f8209",
      "cardholder_id": null,
      "financial_institution_id": 3,
      "financial_institution_lookup_key": "msufcu",
      "clickstream": [
        {
          "url": "/select-merchants",
          "timestamp": "2024-10-15T23:14:46.006Z",
          "page_title": "Select Merchants"
        }
      ],
      "closed_on": "2024-10-15T23:34:34.554Z",
      "custom_data": null,
      "created_on": "2024-10-15T23:14:45.884Z",
      "last_updated_on": "2024-10-15T23:34:34.555Z",
      "_instance": "msu"
    },
    {
      "id": 5732,
      "cuid": "7WF6ZV2JHNZ5G69TF6_460_631b1f04-dd0d-4290-b53e-2d9e7b622055",
      "source": null,
      "successful_jobs": 0,
      "failed_jobs": 0,
      "total_jobs": 0,
      "agent_session_id": "f1f8c0e5-6b9c-4433-b43b-0fdd67779917",
      "cardholder_id": null,
      "financial_institution_id": 3,
      "financial_institution_lookup_key": "msufcu",
      "clickstream": [
        {
          "url": "/select-merchants",
          "timestamp": "2024-10-15T23:36:03.495Z",
          "page_title": "Select Merchants"
        },
        {
          "url": "/select-merchants",
          "timestamp": "2024-10-15T23:36:03.590Z",
          "page_title": "Select Merchants"
        },
        {
          "url": "/select-merchants/missing_fields",
          "timestamp": "2024-10-15T23:36:24.090Z",
          "page_title": "Select Merchants"
        },
        {
          "url": "/select-merchants/missing_fields",
          "timestamp": "2024-10-15T23:36:40.678Z",
          "page_title": "Select Merchants"
        },
        {
          "url": "/select-merchants",
          "timestamp": "2024-10-15T23:36:49.172Z",
          "page_title": "Select Merchants"
        },
        {
          "url": "/user-data-collection",
          "timestamp": "2024-10-15T23:36:49.301Z",
          "page_title": "User Data Collection"
        },
        {
          "url": "/credential-entry",
          "timestamp": "2024-10-15T23:36:49.462Z",
          "page_title": "Credential Entry"
        }
      ],
      "closed_on": "2024-10-15T23:54:34.251Z",
      "custom_data": null,
      "created_on": "2024-10-15T23:36:03.277Z",
      "last_updated_on": "2024-10-15T23:54:34.347Z",
      "_instance": "msu"
    }
  ]
}